{"modified":1775245645,"core":{"items":[{"id":"chaos","name":"Chaos Orb","image":"/gen/image/WzI1LDE0LHsiZiI6IjJESXRlbXMvQ3VycmVuY3kvQ3VycmVuY3lSZXJvbGxSYXJlIiwic2NhbGUiOjF9XQ/46a2347805/CurrencyRerollRare.png","category":"Currency","detailsId":"chaos-orb"},{"id":"divine","name":"Divine Orb","image":"/gen/image/WzI1LDE0LHsiZiI6IjJESXRlbXMvQ3VycmVuY3kvQ3VycmVuY3lNb2RWYWx1ZXMiLCJzY2FsZSI6MX1d/ec48896769/CurrencyModValues.png","category":"Currency","detailsId":"divine-orb"}],"rates":{"divine":0.002908},"primary":"chaos","secondary":"divine"},"lines":[{"id":"accelerating-catalyst","primaryValue":0.2317,"volumePrimaryValue":332.7,"maxVolumeCurrency":"chaos","maxVolumeRate":4.32,"sparkline":{"totalChange":14.84,"data":[18.43,36.94,84.97,47.09,29.26,15.31,14.84]}},{"id":"chaos","primaryValue":1,"volumePrimaryValue":30552364,"maxVolumeCurrency":"divine","maxVolumeRate":343.9,"sparkline":{"totalChange":-20.16,"data":[-3.38,-5.40,-5.18,-6.50,-10.15,-13.40,-20.16]}},{"id":"divine","primaryValue":343.9,"volumePrimaryValue":30552364,"maxVolumeCurrency":"chaos","maxVolumeRate":0.002908,"sparkline":{"totalChange":25.25,"data":[3.52,5.71,5.46,6.95,11.33,15.51,25.25]}},{"id":"blessed","primaryValue":0.2957,"volumePrimaryValue":2631,"maxVolumeCurrency":"chaos","maxVolumeRate":3.38,"sparkline":{"totalChange":35.80,"data":[-6.96,91.41,-3.53,-16.69,-6.66,9.11,35.80]}},{"id":"blessing-general","primaryValue":60.62,"volumePrimaryValue":10042,"maxVolumeCurrency":"chaos","maxVolumeRate":0.01650,"sparkline":{"totalChange":30.17,"data":[-6.02,15.36,11.97,33.58,35.23,36.52,30.17]}},{"id":"abrasive-catalyst","primaryValue":0.1808,"volumePrimaryValue":800.0,"maxVolumeCurrency":"chaos","maxVolumeRate":5.53,"sparkline":{"totalChange":15.51,"data":[3.34,11.27,17.83,35.14,12.62,18.42,15.51]}},{"id":"alch","primaryValue":0.1805,"volumePrimaryValue":35429,"maxVolumeCurrency":"chaos","maxVolumeRate":5.54,"sparkline":{"totalChange":18.29,"data":[6.25,14.12,2.93,20.99,26.53,36.18,18.29]}},{"id":"alt","primaryValue":0.1285,"volumePrimaryValue":88399,"maxVolumeCurrency":"chaos","maxVolumeRate":7.78,"sparkline":{"totalChange":35.17,"data":[0.28,-0.76,10.92,25.66,37.38,28.46,35.17]}},{"id":"ancient-orb","primaryValue":9.43,"volumePrimaryValue":245183,"maxVolumeCurrency":"chaos","maxVolumeRate":0.1061,"sparkline":{"totalChange":-15.29,"data":[-11.91,-16.81,-22.61,-23.40,-18.88,-15.15,-15.29]}},{"id":"annul","primaryValue":12.82,"volumePrimaryValue":265735,"maxVolumeCurrency":"chaos","maxVolumeRate":0.07798,"sparkline":{"totalChange":-2.36,"data":[-1.36,-4.05,-3.11,-4.11,1.48,-5.22,-2.36]}},{"id":"aug","primaryValue":0.09285,"volumePrimaryValue":13745,"maxVolumeCurrency":"chaos","maxVolumeRate":10.77,"sparkline":{"totalChange":16.75,"data":[-0.33,-4.34,4.35,20.38,29.51,23.32,16.75]}},{"id":"awakeners-orb","primaryValue":774.9,"volumePrimaryValue":209102,"maxVolumeCurrency":"chaos","maxVolumeRate":0.001290,"sparkline":{"totalChange":-6.43,"data":[-21.57,-25.15,-22.27,-17.46,-15.25,-12.47,-6.43]}},{"id":"bauble","primaryValue":0.2712,"volumePrimaryValue":6790,"maxVolumeCurrency":"chaos","maxVolumeRate":3.69,"sparkline":{"totalChange":-12.49,"data":[6.84,11.71,-1.53,-17.47,-28.17,-20.81,-12.49]}},{"id":"chance","primaryValue":0.1289,"volumePrimaryValue":56553,"maxVolumeCurrency":"chaos","maxVolumeRate":7.76,"sparkline":{"totalChange":11.81,"data":[3.20,2.21,-5.53,-5.63,7.18,11.19,11.81]}},{"id":"elders-exalted-orb","primaryValue":29.96,"volumePrimaryValue":10071,"maxVolumeCurrency":"chaos","maxVolumeRate":0.03338,"sparkline":{"totalChange":7.49,"data":[-6.41,-4.67,5.15,-3.70,0.04,12.43,7.49]}},{"id":"eldritch-chaos-orb","primaryValue":23.88,"volumePrimaryValue":202719,"maxVolumeCurrency":"chaos","maxVolumeRate":0.04188,"sparkline":{"totalChange":-9.03,"data":[11.61,12.09,0.54,-12.14,-16.87,-21.22,-9.03]}},{"id":"eldritch-exalted-orb","primaryValue":2.64,"volumePrimaryValue":9714,"maxVolumeCurrency":"chaos","maxVolumeRate":0.3785,"sparkline":{"totalChange":-5.54,"data":[5.60,10.52,3.94,2.69,3.44,7.69,-5.54]}},{"id":"eldritch-orb-of-annulment","primaryValue":25.16,"volumePrimaryValue":135388,"maxVolumeCurrency":"chaos","maxVolumeRate":0.03974,"sparkline":{"totalChange":-7.44,"data":[9.31,8.32,-2.54,-12.67,-18.15,-11.14,-7.44]}},{"id":"enkindling-orb","primaryValue":1.76,"volumePrimaryValue":36275,"maxVolumeCurrency":"chaos","maxVolumeRate":0.5690,"sparkline":{"totalChange":2.62,"data":[-3.59,-8.10,-10.60,-2.32,-1.66,-1.58,2.62]}},{"id":"exalted","primaryValue":1.65,"volumePrimaryValue":115965,"maxVolumeCurrency":"chaos","maxVolumeRate":0.6046,"sparkline":{"totalChange":103.9,"data":[10.60,10.33,9.69,13.89,52.27,80.29,103.9]}},{"id":"exceptional-eldritch-ichor","primaryValue":129.6,"volumePrimaryValue":131947,"maxVolumeCurrency":"divine","maxVolumeRate":2.65,"sparkline":{"totalChange":9.68,"data":[-0.15,1.53,2.86,14.15,13.97,19.13,9.68]}},{"id":"fertile-catalyst","primaryValue":9.49,"volumePrimaryValue":46669,"maxVolumeCurrency":"chaos","maxVolumeRate":0.1054,"sparkline":{"totalChange":16.84,"data":[7.23,-4.67,4.92,-0.42,9.06,19.81,16.84]}},{"id":"fracturing-orb","primaryValue":191.6,"volumePrimaryValue":666444,"maxVolumeCurrency":"chaos","maxVolumeRate":0.005219,"sparkline":{"totalChange":0.82,"data":[9.84,15.26,8.65,3.73,-1.83,-2.45,0.82]}},{"id":"fracturing-shard","primaryValue":9.91,"volumePrimaryValue":384.8,"maxVolumeCurrency":"chaos","maxVolumeRate":0.1009,"sparkline":{"totalChange":10.36,"data":[17.84,20.84,19.83,9.41,23.41,8.45,10.36]}},{"id":"fusing","primaryValue":0.1315,"volumePrimaryValue":56453,"maxVolumeCurrency":"chaos","maxVolumeRate":7.60,"sparkline":{"totalChange":15.25,"data":[-11.17,-7.12,-7.26,-8.23,2.39,5.90,15.25]}},{"id":"grand-eldritch-ember","primaryValue":9.20,"volumePrimaryValue":163508,"maxVolumeCurrency":"chaos","maxVolumeRate":0.1087,"sparkline":{"totalChange":-7.58,"data":[-4.11,-2.67,-8.47,-6.54,-5.45,-1.73,-7.58]}},{"id":"grand-eldritch-ichor","primaryValue":2.02,"volumePrimaryValue":66474,"maxVolumeCurrency":"chaos","maxVolumeRate":0.4952,"sparkline":{"totalChange":4.93,"data":[6.24,17.28,2.11,-1.08,6.31,3.45,4.93]}},{"id":"greater-eldritch-ember","primaryValue":0.6692,"volumePrimaryValue":13138,"maxVolumeCurrency":"chaos","maxVolumeRate":1.49,"sparkline":{"totalChange":-22.23,"data":[-16.88,-18.32,-37.48,-41.00,-34.79,-35.56,-22.23]}},{"id":"greater-eldritch-ichor","primaryValue":0.1842,"volumePrimaryValue":2358,"maxVolumeCurrency":"chaos","maxVolumeRate":5.43,"sparkline":{"totalChange":-25.64,"data":[0.55,-4.10,3.49,-22.11,-16.20,-27.49,-25.64]}},{"id":"imbued-catalyst","primaryValue":0.1749,"volumePrimaryValue":719.2,"maxVolumeCurrency":"chaos","maxVolumeRate":5.72,"sparkline":{"totalChange":9.20,"data":[-0.22,5.63,11.53,31.51,6.78,12.74,9.20]}},{"id":"instilling-orb","primaryValue":0.1097,"volumePrimaryValue":1634,"maxVolumeCurrency":"chaos","maxVolumeRate":9.11,"sparkline":{"totalChange":-11.77,"data":[2.66,28.11,-12.37,-21.82,-21.26,10.98,-11.77]}},{"id":"intrinsic-catalyst","primaryValue":0.3342,"volumePrimaryValue":4236,"maxVolumeCurrency":"chaos","maxVolumeRate":2.99,"sparkline":{"totalChange":69.72,"data":[9.48,12.50,38.63,32.33,-4.86,162.6,69.72]}},{"id":"jewellers","primaryValue":0.02066,"volumePrimaryValue":7870,"maxVolumeCurrency":"chaos","maxVolumeRate":48.41,"sparkline":{"totalChange":-25.79,"data":[-8.47,1.34,2.12,-16.85,-6.36,-17.16,-25.79]}},{"id":"lesser-eldritch-ember","primaryValue":0.02930,"volumePrimaryValue":777.7,"maxVolumeCurrency":"chaos","maxVolumeRate":34.13,"sparkline":{"totalChange":-61.11,"data":[-7.35,7.61,-42.51,-55.09,-43.82,-49.77,-61.11]}},{"id":"lesser-eldritch-ichor","primaryValue":0.03537,"volumePrimaryValue":623.8,"maxVolumeCurrency":"chaos","maxVolumeRate":28.27,"sparkline":{"totalChange":-43.79,"data":[-1.55,-29.15,-35.42,-54.00,-39.02,-41.68,-43.79]}},{"id":"mavens-chisel-of-avarice","primaryValue":89.18,"volumePrimaryValue":414789,"maxVolumeCurrency":"chaos","maxVolumeRate":0.01121,"sparkline":{"totalChange":-40.13,"data":[-14.50,-8.11,-13.54,-23.70,-34.14,-38.63,-40.13]}},{"id":"mavens-chisel-of-scarabs","primaryValue":27.13,"volumePrimaryValue":91346,"maxVolumeCurrency":"chaos","maxVolumeRate":0.03686,"sparkline":{"totalChange":1.92,"data":[-4.37,-8.45,15.13,1.26,-7.76,-1.25,1.92]}},{"id":"orb-of-binding","primaryValue":0.08720,"volumePrimaryValue":817.2,"maxVolumeCurrency":"chaos","maxVolumeRate":11.47,"sparkline":{"totalChange":100.2,"data":[3.41,5.52,-2.55,26.19,23.38,33.37,100.2]}},{"id":"orb-of-conflict","primaryValue":606.9,"volumePrimaryValue":838280,"maxVolumeCurrency":"divine","maxVolumeRate":0.5667,"sparkline":{"totalChange":1.09,"data":[-5.25,-5.96,-4.16,-7.40,-9.15,-5.21,1.09]}},{"id":"orb-of-intention","primaryValue":0.1111,"volumePrimaryValue":1.0,"maxVolumeCurrency":"chaos","maxVolumeRate":9,"sparkline":{"totalChange":-89.62,"data":[-34.78,-37.82,-65.13,-50.23,-65.68,-53.97,-89.62]}},{"id":"orb-of-remembrance","primaryValue":129.8,"volumePrimaryValue":77461,"maxVolumeCurrency":"chaos","maxVolumeRate":0.007705,"sparkline":{"totalChange":52.03,"data":[4.35,6.01,11.70,-7.56,6.55,25.78,52.03]}},{"id":"orb-of-unmaking","primaryValue":0.2599,"volumePrimaryValue":14455,"maxVolumeCurrency":"chaos","maxVolumeRate":3.85,"sparkline":{"totalChange":32.20,"data":[-6.04,0.22,-5.79,0.75,5.23,57.17,32.20]}},{"id":"orb-of-unravelling","primaryValue":6.45,"volumePrimaryValue":944.3,"maxVolumeCurrency":"chaos","maxVolumeRate":0.1550,"sparkline":{"totalChange":-10.09,"data":[2.24,-5.75,-8.62,-10.19,-8.75,-17.15,-10.09]}},{"id":"primal-lifeforce","primaryValue":0.04724,"volumePrimaryValue":1078443,"maxVolumeCurrency":"divine","maxVolumeRate":7279,"sparkline":{"totalChange":14.70,"data":[0.84,2.46,20.07,26.19,21.20,11.92,14.70]}},{"id":"redeemers-exalted-orb","primaryValue":33.77,"volumePrimaryValue":2786,"maxVolumeCurrency":"chaos","maxVolumeRate":0.02962,"sparkline":{"totalChange":9.57,"data":[3.25,17.63,-2.18,27.58,25.52,3.92,9.57]}},{"id":"reflecting-mist","primaryValue":16216,"volumePrimaryValue":4016120,"maxVolumeCurrency":"divine","maxVolumeRate":0.02121,"sparkline":{"totalChange":27.83,"data":[-1.77,-3.27,8.05,16.99,19.09,22.82,27.83]}},{"id":"regal","primaryValue":0.1735,"volumePrimaryValue":3716,"maxVolumeCurrency":"chaos","maxVolumeRate":5.76,"sparkline":{"totalChange":-0.70,"data":[-10.77,-10.41,-0.57,-7.09,4.37,1.74,-0.70]}},{"id":"regret","primaryValue":0.7506,"volumePrimaryValue":46044,"maxVolumeCurrency":"chaos","maxVolumeRate":1.33,"sparkline":{"totalChange":19.70,"data":[3.93,9.93,-2.42,2.86,12.45,15.01,19.70]}},{"id":"sacred-lifeforce","primaryValue":44.17,"volumePrimaryValue":44011,"maxVolumeCurrency":"chaos","maxVolumeRate":0.02264,"sparkline":{"totalChange":-7.23,"data":[-13.02,-13.41,-12.35,-7.48,-7.69,-8.64,-7.23]}},{"id":"sandswept-lifeforce","primaryValue":15.24,"volumePrimaryValue":89518,"maxVolumeCurrency":"chaos","maxVolumeRate":0.06562,"sparkline":{"totalChange":2.91,"data":[-14.32,-14.19,-8.25,1.18,-1.17,-1.42,2.91]}},{"id":"scour","primaryValue":0.7225,"volumePrimaryValue":139957,"maxVolumeCurrency":"chaos","maxVolumeRate":1.38,"sparkline":{"totalChange":25.18,"data":[7.28,2.34,-1.16,1.08,17.58,25.26,25.18]}},{"id":"scrap","primaryValue":0.04690,"volumePrimaryValue":2066,"maxVolumeCurrency":"chaos","maxVolumeRate":21.32,"sparkline":{"totalChange":52.70,"data":[-3.60,-7.87,4.80,14.60,-4.05,-1.60,52.70]}},{"id":"shapers-exalted-orb","primaryValue":79.89,"volumePrimaryValue":27802,"maxVolumeCurrency":"chaos","maxVolumeRate":0.01252,"sparkline":{"totalChange":-6.26,"data":[14.92,2.13,-8.37,-19.46,-15.49,-8.80,-6.26]}},{"id":"tainted-blacksmiths-whetstone","primaryValue":0.3594,"volumePrimaryValue":369.7,"maxVolumeCurrency":"chaos","maxVolumeRate":2.78,"sparkline":{"totalChange":-3.42,"data":[45.52,-3.02,4.47,-11.10,-5.69,-10.66,-3.42]}},{"id":"tainted-exalted-orb","primaryValue":74.33,"volumePrimaryValue":10295,"maxVolumeCurrency":"chaos","maxVolumeRate":0.01345,"sparkline":{"totalChange":101.0,"data":[12.66,1.90,-3.58,59.52,74.92,86.67,101.0]}},{"id":"tainted-orb-of-fusing","primaryValue":3.59,"volumePrimaryValue":12027,"maxVolumeCurrency":"chaos","maxVolumeRate":0.2784,"sparkline":{"totalChange":-7.86,"data":[-0.40,-1.71,-7.15,-8.26,-9.75,17.16,-7.86]}},{"id":"tempering-catalyst","primaryValue":0.9386,"volumePrimaryValue":2484,"maxVolumeCurrency":"chaos","maxVolumeRate":1.07,"sparkline":{"totalChange":85.19,"data":[8.28,124.3,52.11,65.04,38.82,56.86,85.19]}},{"id":"turbulent-catalyst","primaryValue":0.2176,"volumePrimaryValue":951.7,"maxVolumeCurrency":"chaos","maxVolumeRate":4.60,"sparkline":{"totalChange":33.38,"data":[44.70,24.91,55.50,43.24,11.68,15.14,33.38]}},{"id":"veiled-exalted-orb","primaryValue":8771,"volumePrimaryValue":1052478,"maxVolumeCurrency":"divine","maxVolumeRate":0.03921,"sparkline":{"totalChange":33.77,"data":[9.77,15.13,20.70,38.16,63.97,57.87,33.77]}},{"id":"vivid-lifeforce","primaryValue":0.09359,"volumePrimaryValue":5975202,"maxVolumeCurrency":"divine","maxVolumeRate":3675,"sparkline":{"totalChange":18.40,"data":[-6.35,-1.64,4.94,12.25,21.97,22.18,18.40]}},{"id":"wild-lifeforce","primaryValue":0.03411,"volumePrimaryValue":572495,"maxVolumeCurrency":"divine","maxVolumeRate":10081,"sparkline":{"totalChange":5.54,"data":[-2.35,-5.56,-0.61,2.00,6.08,3.99,5.54]}},{"id":"chrome","primaryValue":0.06678,"volumePrimaryValue":34290,"maxVolumeCurrency":"chaos","maxVolumeRate":14.97,"sparkline":{"totalChange":-11.95,"data":[-5.56,-9.13,-10.26,-19.83,-15.13,-15.26,-11.95]}},{"id":"cluster-fog","primaryValue":290.7,"volumePrimaryValue":1008619,"maxVolumeCurrency":"chaos","maxVolumeRate":0.003440,"sparkline":{"totalChange":162.3,"data":[25.93,84.60,143.4,110.2,129.9,160.2,162.3]}},{"id":"crusaders-exalted-orb","primaryValue":85.53,"volumePrimaryValue":8781,"maxVolumeCurrency":"chaos","maxVolumeRate":0.01169,"sparkline":{"totalChange":53.25,"data":[-3.72,7.53,14.62,54.22,101.9,67.02,53.25]}},{"id":"dextral-catalyst","primaryValue":86.20,"volumePrimaryValue":120560,"maxVolumeCurrency":"chaos","maxVolumeRate":0.01160,"sparkline":{"totalChange":24.03,"data":[-3.68,-4.30,6.17,14.17,17.04,21.27,24.03]}},{"id":"hinekoras-lock","primaryValue":41517,"volumePrimaryValue":11728581,"maxVolumeCurrency":"divine","maxVolumeRate":0.008284,"sparkline":{"totalChange":6.65,"data":[-10.99,-5.67,-1.63,10.63,13.40,12.74,6.65]}},{"id":"exceptional-eldritch-ember","primaryValue":126.6,"volumePrimaryValue":136303,"maxVolumeCurrency":"divine","maxVolumeRate":2.72,"sparkline":{"totalChange":-5.60,"data":[0.89,-1.58,-4.73,-7.72,-7.47,-5.07,-5.60]}},{"id":"foulborn-exalted-orb","primaryValue":1207,"volumePrimaryValue":206804,"maxVolumeCurrency":"divine","maxVolumeRate":0.2849,"sparkline":{"totalChange":-8.32,"data":[-6.05,-12.75,-17.57,-19.63,-15.96,10.03,-8.32]}},{"id":"foulborn-orb-of-augmentation","primaryValue":3.10,"volumePrimaryValue":2792,"maxVolumeCurrency":"chaos","maxVolumeRate":0.3230,"sparkline":{"totalChange":35.16,"data":[1.14,6.25,9.49,32.75,16.46,27.28,35.16]}},{"id":"foulborn-regal-orb","primaryValue":5.69,"volumePrimaryValue":2624,"maxVolumeCurrency":"chaos","maxVolumeRate":0.1758,"sparkline":{"totalChange":-28.76,"data":[1.18,-4.02,-14.44,-11.97,-27.18,-36.44,-28.76]}},{"id":"gcp","primaryValue":2.92,"volumePrimaryValue":274920,"maxVolumeCurrency":"chaos","maxVolumeRate":0.3421,"sparkline":{"totalChange":23.89,"data":[7.51,13.64,2.38,-4.25,-4.41,-2.53,23.89]}},{"id":"hunters-exalted-orb","primaryValue":167.8,"volumePrimaryValue":14626,"maxVolumeCurrency":"chaos","maxVolumeRate":0.005960,"sparkline":{"totalChange":39.23,"data":[-6.32,4.82,-0.86,39.01,36.46,30.43,39.23]}},{"id":"mavens-chisel-of-divination","primaryValue":278.3,"volumePrimaryValue":820965,"maxVolumeCurrency":"chaos","maxVolumeRate":0.003593,"sparkline":{"totalChange":1852,"data":[18.30,89.42,315.9,910.4,1277,1783,1852]}},{"id":"mavens-chisel-of-procurement","primaryValue":3.48,"volumePrimaryValue":21119,"maxVolumeCurrency":"chaos","maxVolumeRate":0.2873,"sparkline":{"totalChange":-4.69,"data":[-3.64,-4.56,-12.81,-0.55,-6.79,-12.79,-4.69]}},{"id":"mavens-chisel-of-proliferation","primaryValue":45.46,"volumePrimaryValue":201114,"maxVolumeCurrency":"chaos","maxVolumeRate":0.02200,"sparkline":{"totalChange":-10.17,"data":[-4.03,-6.34,8.20,6.43,-6.27,-13.77,-10.17]}},{"id":"mavens-orb","primaryValue":2996,"volumePrimaryValue":905228,"maxVolumeCurrency":"divine","maxVolumeRate":0.1148,"sparkline":{"totalChange":47.56,"data":[-6.61,-19.40,-17.15,13.10,42.96,51.90,47.56]}},{"id":"mirror","primaryValue":329530,"volumePrimaryValue":81448820,"maxVolumeCurrency":"divine","maxVolumeRate":0.001044,"sparkline":{"totalChange":17.92,"data":[-4.92,-1.90,3.81,7.78,15.49,17.96,17.92]}},{"id":"mirror-shard","primaryValue":16662,"volumePrimaryValue":6812163,"maxVolumeCurrency":"divine","maxVolumeRate":0.02064,"sparkline":{"totalChange":19.29,"data":[-4.15,-1.29,4.79,9.45,18.80,19.35,19.29]}},{"id":"noxious-catalyst","primaryValue":0.1831,"volumePrimaryValue":905.0,"maxVolumeCurrency":"chaos","maxVolumeRate":5.46,"sparkline":{"totalChange":-2.75,"data":[0.56,-4.28,9.44,15.88,-7.57,7.31,-2.75]}},{"id":"portal","primaryValue":0.05349,"volumePrimaryValue":8717,"maxVolumeCurrency":"chaos","maxVolumeRate":18.69,"sparkline":{"totalChange":24.93,"data":[-16.82,-13.39,51.81,35.70,178.6,21.38,24.93]}},{"id":"prismatic-catalyst","primaryValue":17.25,"volumePrimaryValue":84026,"maxVolumeCurrency":"chaos","maxVolumeRate":0.05796,"sparkline":{"totalChange":25.12,"data":[13.16,14.20,27.99,40.05,27.41,27.31,25.12]}},{"id":"rogues-marker","primaryValue":0.002428,"volumePrimaryValue":92124,"maxVolumeCurrency":"chaos","maxVolumeRate":411.9,"sparkline":{"totalChange":-7.31,"data":[-1.04,-7.25,0.62,0.09,-3.72,0.81,-7.31]}},{"id":"sacred-orb","primaryValue":40.37,"volumePrimaryValue":55136,"maxVolumeCurrency":"chaos","maxVolumeRate":0.02477,"sparkline":{"totalChange":14.39,"data":[-3.51,6.92,2.18,3.50,10.53,4.26,14.39]}},{"id":"sinistral-catalyst","primaryValue":24.25,"volumePrimaryValue":45873,"maxVolumeCurrency":"chaos","maxVolumeRate":0.04124,"sparkline":{"totalChange":35.06,"data":[45.36,9.50,18.96,26.13,13.24,24.53,35.06]}},{"id":"stacked-deck","primaryValue":4.67,"volumePrimaryValue":4960897,"maxVolumeCurrency":"divine","maxVolumeRate":73.64,"sparkline":{"totalChange":12.50,"data":[-5.93,-4.48,-1.13,5.10,7.96,9.22,12.50]}},{"id":"tailoring-orb","primaryValue":243.6,"volumePrimaryValue":299373,"maxVolumeCurrency":"divine","maxVolumeRate":1.41,"sparkline":{"totalChange":-36.79,"data":[13.20,14.52,3.56,-4.81,-16.53,-19.93,-36.79]}},{"id":"tainted-armourers-scrap","primaryValue":0.6485,"volumePrimaryValue":3081,"maxVolumeCurrency":"chaos","maxVolumeRate":1.54,"sparkline":{"totalChange":-1.34,"data":[7.08,24.18,13.41,4.74,45.02,-9.79,-1.34]}},{"id":"tainted-catalyst","primaryValue":6.59,"volumePrimaryValue":40816,"maxVolumeCurrency":"chaos","maxVolumeRate":0.1518,"sparkline":{"totalChange":88.65,"data":[6.04,6.80,50.43,68.00,60.24,86.83,88.65]}},{"id":"tainted-chaos-orb","primaryValue":4.52,"volumePrimaryValue":2630,"maxVolumeCurrency":"chaos","maxVolumeRate":0.2211,"sparkline":{"totalChange":45.72,"data":[-13.09,-2.83,-0.99,0.80,-1.30,-19.38,45.72]}},{"id":"tainted-chromatic-orb","primaryValue":2.33,"volumePrimaryValue":30309,"maxVolumeCurrency":"chaos","maxVolumeRate":0.4285,"sparkline":{"totalChange":53.27,"data":[-10.11,-9.56,-16.94,-18.09,7.51,12.89,53.27]}},{"id":"tainted-divine-orb","primaryValue":379.3,"volumePrimaryValue":734161,"maxVolumeCurrency":"chaos","maxVolumeRate":0.002636,"sparkline":{"totalChange":9.88,"data":[3.60,4.30,10.04,7.64,11.78,8.23,9.88]}},{"id":"tainted-divine-teardrop","primaryValue":357.4,"volumePrimaryValue":32766,"maxVolumeCurrency":"chaos","maxVolumeRate":0.002798,"sparkline":{"totalChange":-19.74,"data":[-21.62,-21.97,-4.03,-20.27,-34.75,-25.86,-19.74]}},{"id":"tainted-jewellers-orb","primaryValue":0.4729,"volumePrimaryValue":1655,"maxVolumeCurrency":"chaos","maxVolumeRate":2.11,"sparkline":{"totalChange":-27.41,"data":[-12.66,-17.50,-18.95,-17.19,-4.09,-12.24,-27.41]}},{"id":"tainted-mythic-orb","primaryValue":4.28,"volumePrimaryValue":4294,"maxVolumeCurrency":"chaos","maxVolumeRate":0.2335,"sparkline":{"totalChange":11.79,"data":[1.89,-10.72,-9.74,7.19,7.85,-1.08,11.79]}},{"id":"tempering-orb","primaryValue":458.3,"volumePrimaryValue":646092,"maxVolumeCurrency":"divine","maxVolumeRate":0.7504,"sparkline":{"totalChange":-12.11,"data":[-3.42,0.99,-8.04,-5.56,0.40,2.14,-12.11]}},{"id":"transmute","primaryValue":0.009459,"volumePrimaryValue":2738,"maxVolumeCurrency":"chaos","maxVolumeRate":105.7,"sparkline":{"totalChange":-11.21,"data":[-2.22,-10.13,-6.11,4.59,3.97,-0.84,-11.21]}},{"id":"unstable-catalyst","primaryValue":2.00,"volumePrimaryValue":7991,"maxVolumeCurrency":"chaos","maxVolumeRate":0.5008,"sparkline":{"totalChange":102.3,"data":[25.40,26.86,32.33,60.68,96.92,59.67,102.3]}},{"id":"vaal","primaryValue":0.7973,"volumePrimaryValue":96347,"maxVolumeCurrency":"chaos","maxVolumeRate":1.25,"sparkline":{"totalChange":22.73,"data":[6.12,2.79,-5.35,-6.12,-3.72,13.72,22.73]}},{"id":"veiled-chaos-orb","primaryValue":196.1,"volumePrimaryValue":199302,"maxVolumeCurrency":"chaos","maxVolumeRate":0.005099,"sparkline":{"totalChange":61.30,"data":[-0.56,-4.88,7.12,20.60,60.09,51.63,61.30]}},{"id":"warlords-exalted-orb","primaryValue":244.8,"volumePrimaryValue":24195,"maxVolumeCurrency":"chaos","maxVolumeRate":0.004085,"sparkline":{"totalChange":27.32,"data":[-5.68,9.51,19.52,24.84,10.98,10.29,27.32]}},{"id":"whetstone","primaryValue":0.01059,"volumePrimaryValue":258.8,"maxVolumeCurrency":"chaos","maxVolumeRate":94.44,"sparkline":{"totalChange":-2.68,"data":[4.73,-9.61,-3.41,22.04,18.93,32.34,-2.68]}},{"id":"wisdom","primaryValue":0.006961,"volumePrimaryValue":801.5,"maxVolumeCurrency":"chaos","maxVolumeRate":143.7,"sparkline":{"totalChange":-8.16,"data":[-14.57,3.23,19.33,-0.29,33.77,-0.77,-8.16]}}],"items":[{"id":"accelerating-catalyst","name":"Accelerating Catalyst","image":"/gen/image/WzI1LDE0LHsiZiI6IjJESXRlbXMvQ3VycmVuY3kvQ2F0YWx5c3RzL1NwZWVkTW9kaWZpZXJDYXRhbHlzdCIsInNjYWxlIjoxfV0/6493f34e78/SpeedModifierCatalyst.png","category":"Catalysts","detailsId":"accelerating-catalyst"},{"id":"chaos","name":"Chaos Orb","image":"/gen/image/WzI1LDE0LHsiZiI6IjJESXRlbXMvQ3VycmVuY3kvQ3VycmVuY3lSZXJvbGxSYXJlIiwic2NhbGUiOjF9XQ/46a2347805/CurrencyRerollRare.png","category":"Currency","detailsId":"chaos-orb"},{"id":"divine","name":"Divine Orb","image":"/gen/image/WzI1LDE0LHsiZiI6IjJESXRlbXMvQ3VycmVuY3kvQ3VycmVuY3lNb2RWYWx1ZXMiLCJzY2FsZSI6MX1d/ec48896769/CurrencyModValues.png","category":"Currency","detailsId":"divine-orb"},{"id":"blessed","name":"Blessed Orb","image":"/gen/image/WzI1LDE0LHsiZiI6IjJESXRlbXMvQ3VycmVuY3kvQ3VycmVuY3lJbXBsaWNpdE1vZCIsInNjYWxlIjoxfV0/48e700cc20/CurrencyImplicitMod.png","category":"Currency","detailsId":"blessed-orb"},{"id":"blessing-general","name":"Flesh of Xesht","image":"/gen/image/WzI1LDE0LHsiZiI6IjJESXRlbXMvQ3VycmVuY3kvQ2hheXVsYS9Db3JlQnJlYWNoQ3VycmVuY3kiLCJzY2FsZSI6MX1d/32fda5c220/CoreBreachCurrency.png","category":"Currency","detailsId":"flesh-of-xesht"},{"id":"abrasive-catalyst","name":"Abrasive Catalyst","image":"/gen/image/WzI1LDE0LHsiZiI6IjJESXRlbXMvQ3VycmVuY3kvQ2F0YWx5c3RzL0FicmFzaXZlQ2F0YWx5c3QiLCJzY2FsZSI6MX1d/aca49c3cc0/AbrasiveCatalyst.png","category":"Catalysts","detailsId":"abrasive-catalyst"},{"id":"alch","name":"Orb of Alchemy","image":"/gen/image/WzI1LDE0LHsiZiI6IjJESXRlbXMvQ3VycmVuY3kvQ3VycmVuY3lVcGdyYWRlVG9SYXJlIiwic2NhbGUiOjF9XQ/0c72cd1d44/CurrencyUpgradeToRare.png","category":"Currency","detailsId":"orb-of-alchemy"},{"id":"alt","name":"Orb of Alteration","image":"/gen/image/WzI1LDE0LHsiZiI6IjJESXRlbXMvQ3VycmVuY3kvQ3VycmVuY3lSZXJvbGxNYWdpYyIsInNjYWxlIjoxfV0/6308fc8ca2/CurrencyRerollMagic.png","category":"Currency","detailsId":"orb-of-alteration"},{"id":"ancient-orb","name":"Ancient Orb","image":"/gen/image/WzI1LDE0LHsiZiI6IjJESXRlbXMvQ3VycmVuY3kvQW5jaWVudE9yYiIsInNjYWxlIjoxfV0/83015d0dc9/AncientOrb.png","category":"Currency","detailsId":"ancient-orb"},{"id":"annul","name":"Orb of Annulment","image":"/gen/image/WzI1LDE0LHsiZiI6IjJESXRlbXMvQ3VycmVuY3kvQW5udWxsT3JiIiwic2NhbGUiOjF9XQ/0858a418ac/AnnullOrb.png","category":"Currency","detailsId":"orb-of-annulment"},{"id":"aug","name":"Orb of Augmentation","image":"/gen/image/WzI1LDE0LHsiZiI6IjJESXRlbXMvQ3VycmVuY3kvQ3VycmVuY3lBZGRNb2RUb01hZ2ljIiwic2NhbGUiOjF9XQ/d879c15321/CurrencyAddModToMagic.png","category":"Currency","detailsId":"orb-of-augmentation"},{"id":"awakeners-orb","name":"Awakener's Orb","image":"/gen/image/WzI1LDE0LHsiZiI6IjJESXRlbXMvQ3VycmVuY3kvVHJhbnNmZXJPcmIiLCJzY2FsZSI6MX1d/f3b1c1566f/TransferOrb.png","category":"Currency","detailsId":"awakeners-orb"},{"id":"bauble","name":"Glassblower's Bauble","image":"/gen/image/WzI1LDE0LHsiZiI6IjJESXRlbXMvQ3VycmVuY3kvQ3VycmVuY3lGbGFza1F1YWxpdHkiLCJzY2FsZSI6MX1d/59e57027e5/CurrencyFlaskQuality.png","category":"Currency","detailsId":"glassblowers-bauble"},{"id":"chance","name":"Orb of Chance","image":"/gen/image/WzI1LDE0LHsiZiI6IjJESXRlbXMvQ3VycmVuY3kvQ3VycmVuY3lVcGdyYWRlUmFuZG9tbHkiLCJzY2FsZSI6MX1d/a3f9bf0917/CurrencyUpgradeRandomly.png","category":"Currency","detailsId":"orb-of-chance"},{"id":"elders-exalted-orb","name":"Elder's Exalted Orb","image":"/gen/image/WzI1LDE0LHsiZiI6IjJESXRlbXMvQ3VycmVuY3kvU2VjcmV0c29mdGhlQXRsYXMvRWxkZXJFeGFsdGVkT3JiIiwic2NhbGUiOjF9XQ/06f31a048c/ElderExaltedOrb.png","category":"Currency","detailsId":"elders-exalted-orb"},{"id":"eldritch-chaos-orb","name":"Eldritch Chaos Orb","image":"/gen/image/WzI1LDE0LHsiZiI6IjJESXRlbXMvQ3VycmVuY3kvRWxkcml0Y2hDaGFvc09yYiIsInNjYWxlIjoxfV0/98091fc653/EldritchChaosOrb.png","category":"Currency","detailsId":"eldritch-chaos-orb"},{"id":"eldritch-exalted-orb","name":"Eldritch Exalted Orb","image":"/gen/image/WzI1LDE0LHsiZiI6IjJESXRlbXMvQ3VycmVuY3kvRWxkcml0Y2hFeGFsdGVkT3JiIiwic2NhbGUiOjF9XQ/2da131e652/EldritchExaltedOrb.png","category":"Currency","detailsId":"eldritch-exalted-orb"},{"id":"eldritch-orb-of-annulment","name":"Eldritch Orb of Annulment","image":"/gen/image/WzI1LDE0LHsiZiI6IjJESXRlbXMvQ3VycmVuY3kvRWxkcml0Y2hBbm51bG1lbnRPcmIiLCJzY2FsZSI6MX1d/b58add03eb/EldritchAnnulmentOrb.png","category":"Currency","detailsId":"eldritch-orb-of-annulment"},{"id":"enkindling-orb","name":"Enkindling Orb","image":"/gen/image/WzI1LDE0LHsiZiI6IjJESXRlbXMvQ3VycmVuY3kvRXhwZWRpdGlvbi9GbGFza1BsYXRlIiwic2NhbGUiOjF9XQ/7c1a584a8d/FlaskPlate.png","category":"Currency","detailsId":"enkindling-orb"},{"id":"exalted","name":"Exalted Orb","image":"/gen/image/WzI1LDE0LHsiZiI6IjJESXRlbXMvQ3VycmVuY3kvQ3VycmVuY3lBZGRNb2RUb1JhcmUiLCJzY2FsZSI6MX1d/33f2656aea/CurrencyAddModToRare.png","category":"Currency","detailsId":"exalted-orb"},{"id":"exceptional-eldritch-ichor","name":"Exceptional Eldritch Ichor","image":"/gen/image/WzI1LDE0LHsiZiI6IjJESXRlbXMvQ3VycmVuY3kvVGFuZ2xlT3JiUmFuazQiLCJzY2FsZSI6MX1d/dcf73ecd8e/TangleOrbRank4.png","category":"Currency","detailsId":"exceptional-eldritch-ichor"},{"id":"fertile-catalyst","name":"Fertile Catalyst","image":"/gen/image/WzI1LDE0LHsiZiI6IjJESXRlbXMvQ3VycmVuY3kvQ2F0YWx5c3RzL0ZlcnRpbGVDYXRhbHlzdCIsInNjYWxlIjoxfV0/74603722ac/FertileCatalyst.png","category":"Catalysts","detailsId":"fertile-catalyst"},{"id":"fracturing-orb","name":"Fracturing Orb","image":"/gen/image/WzI1LDE0LHsiZiI6IjJESXRlbXMvQ3VycmVuY3kvRnJhY3R1cmluZ09yYkNvbWJpbmVkIiwic2NhbGUiOjF9XQ/3fb18e8a5b/FracturingOrbCombined.png","category":"Currency","detailsId":"fracturing-orb"},{"id":"fracturing-shard","name":"Fracturing Shard","image":"/gen/image/WzI1LDE0LHsiZiI6IjJESXRlbXMvQ3VycmVuY3kvRnJhY3R1cmluZ09yYlNoYXJkIiwic2NhbGUiOjF9XQ/34fdc6a813/FracturingOrbShard.png","category":"Currency","detailsId":"fracturing-shard"},{"id":"fusing","name":"Orb of Fusing","image":"/gen/image/WzI1LDE0LHsiZiI6IjJESXRlbXMvQ3VycmVuY3kvQ3VycmVuY3lSZXJvbGxTb2NrZXRMaW5rcyIsInNjYWxlIjoxfV0/c5e1959880/CurrencyRerollSocketLinks.png","category":"Currency","detailsId":"orb-of-fusing"},{"id":"grand-eldritch-ember","name":"Grand Eldritch Ember","image":"/gen/image/WzI1LDE0LHsiZiI6IjJESXRlbXMvQ3VycmVuY3kvQ2xlYW5zaW5nRmlyZU9yYlJhbmszIiwic2NhbGUiOjF9XQ/0486f1ac82/CleansingFireOrbRank3.png","category":"Currency","detailsId":"grand-eldritch-ember"},{"id":"grand-eldritch-ichor","name":"Grand Eldritch Ichor","image":"/gen/image/WzI1LDE0LHsiZiI6IjJESXRlbXMvQ3VycmVuY3kvVGFuZ2xlT3JiUmFuazMiLCJzY2FsZSI6MX1d/199f3b36f3/TangleOrbRank3.png","category":"Currency","detailsId":"grand-eldritch-ichor"},{"id":"greater-eldritch-ember","name":"Greater Eldritch Ember","image":"/gen/image/WzI1LDE0LHsiZiI6IjJESXRlbXMvQ3VycmVuY3kvQ2xlYW5zaW5nRmlyZU9yYlJhbmsyIiwic2NhbGUiOjF9XQ/698817b93d/CleansingFireOrbRank2.png","category":"Currency","detailsId":"greater-eldritch-ember"},{"id":"greater-eldritch-ichor","name":"Greater Eldritch Ichor","image":"/gen/image/WzI1LDE0LHsiZiI6IjJESXRlbXMvQ3VycmVuY3kvVGFuZ2xlT3JiUmFuazIiLCJzY2FsZSI6MX1d/689d1897c7/TangleOrbRank2.png","category":"Currency","detailsId":"greater-eldritch-ichor"},{"id":"imbued-catalyst","name":"Imbued Catalyst","image":"/gen/image/WzI1LDE0LHsiZiI6IjJESXRlbXMvQ3VycmVuY3kvQ2F0YWx5c3RzL0ltYnVlZENhdGFseXN0Iiwic2NhbGUiOjF9XQ/cce071aa45/ImbuedCatalyst.png","category":"Catalysts","detailsId":"imbued-catalyst"},{"id":"instilling-orb","name":"Instilling Orb","image":"/gen/image/WzI1LDE0LHsiZiI6IjJESXRlbXMvQ3VycmVuY3kvRXhwZWRpdGlvbi9GbGFza0luamVjdG9yIiwic2NhbGUiOjF9XQ/efc518b1be/FlaskInjector.png","category":"Currency","detailsId":"instilling-orb"},{"id":"intrinsic-catalyst","name":"Intrinsic Catalyst","image":"/gen/image/WzI1LDE0LHsiZiI6IjJESXRlbXMvQ3VycmVuY3kvQ2F0YWx5c3RzL0ludHJpbnNpY0NhdGFseXN0Iiwic2NhbGUiOjF9XQ/cea67fbce2/IntrinsicCatalyst.png","category":"Catalysts","detailsId":"intrinsic-catalyst"},{"id":"jewellers","name":"Jeweller's Orb","image":"/gen/image/WzI1LDE0LHsiZiI6IjJESXRlbXMvQ3VycmVuY3kvQ3VycmVuY3lSZXJvbGxTb2NrZXROdW1iZXJzIiwic2NhbGUiOjF9XQ/ba411ff58a/CurrencyRerollSocketNumbers.png","category":"Currency","detailsId":"jewellers-orb"},{"id":"lesser-eldritch-ember","name":"Lesser Eldritch Ember","image":"/gen/image/WzI1LDE0LHsiZiI6IjJESXRlbXMvQ3VycmVuY3kvQ2xlYW5zaW5nRmlyZU9yYlJhbmsxIiwic2NhbGUiOjF9XQ/c7df0e0316/CleansingFireOrbRank1.png","category":"Currency","detailsId":"lesser-eldritch-ember"},{"id":"lesser-eldritch-ichor","name":"Lesser Eldritch Ichor","image":"/gen/image/WzI1LDE0LHsiZiI6IjJESXRlbXMvQ3VycmVuY3kvVGFuZ2xlT3JiUmFuazEiLCJzY2FsZSI6MX1d/70e5e53590/TangleOrbRank1.png","category":"Currency","detailsId":"lesser-eldritch-ichor"},{"id":"mavens-chisel-of-avarice","name":"Maven's Chisel of Avarice","image":"/gen/image/WzI1LDE0LHsiZiI6IjJESXRlbXMvQ3VycmVuY3kvTWF2ZW5DaGlzZWw0Iiwic2NhbGUiOjF9XQ/d878502dc7/MavenChisel4.png","category":"Currency","detailsId":"mavens-chisel-of-avarice"},{"id":"mavens-chisel-of-scarabs","name":"Maven's Chisel of Scarabs","image":"/gen/image/WzI1LDE0LHsiZiI6IjJESXRlbXMvQ3VycmVuY3kvTWF2ZW5DaGlzZWwzIiwic2NhbGUiOjF9XQ/a7a9ac8f01/MavenChisel3.png","category":"Currency","detailsId":"mavens-chisel-of-scarabs"},{"id":"orb-of-binding","name":"Orb of Binding","image":"/gen/image/WzI1LDE0LHsiZiI6IjJESXRlbXMvQ3VycmVuY3kvQmluZGluZ09yYiIsInNjYWxlIjoxfV0/aac9579bd2/BindingOrb.png","category":"Currency","detailsId":"orb-of-binding"},{"id":"orb-of-conflict","name":"Orb of Conflict","image":"/gen/image/WzI1LDE0LHsiZiI6IjJESXRlbXMvQ3VycmVuY3kvQ29uZmxpY3RPcmJSYW5rMSIsInNjYWxlIjoxfV0/7e02c990fc/ConflictOrbRank1.png","category":"Currency","detailsId":"orb-of-conflict"},{"id":"orb-of-intention","name":"Orb of Intention","image":"/gen/image/WzI1LDE0LHsiZiI6IjJESXRlbXMvQ3VycmVuY3kvU2VjcmV0c29mdGhlQXRsYXMvWmFuYVBpbm5hY2xlT3JiMyIsInNjYWxlIjoxfV0/50ef504807/ZanaPinnacleOrb3.png","category":"Currency","detailsId":"orb-of-intention"},{"id":"orb-of-remembrance","name":"Orb of Remembrance","image":"/gen/image/WzI1LDE0LHsiZiI6IjJESXRlbXMvQ3VycmVuY3kvU2VjcmV0c29mdGhlQXRsYXMvWmFuYVBpbm5hY2xlT3JiMSIsInNjYWxlIjoxfV0/c91033d1be/ZanaPinnacleOrb1.png","category":"Currency","detailsId":"orb-of-remembrance"},{"id":"orb-of-unmaking","name":"Orb of Unmaking","image":"/gen/image/WzI1LDE0LHsiZiI6IjJESXRlbXMvQ3VycmVuY3kvUmVncmV0T3JiIiwic2NhbGUiOjF9XQ/beae1b00c7/RegretOrb.png","category":"Currency","detailsId":"orb-of-unmaking"},{"id":"orb-of-unravelling","name":"Orb of Unravelling","image":"/gen/image/WzI1LDE0LHsiZiI6IjJESXRlbXMvQ3VycmVuY3kvU2VjcmV0c29mdGhlQXRsYXMvWmFuYVBpbm5hY2xlT3JiMiIsInNjYWxlIjoxfV0/68c2c8e04c/ZanaPinnacleOrb2.png","category":"Currency","detailsId":"orb-of-unravelling"},{"id":"primal-lifeforce","name":"Primal Crystallised Lifeforce","image":"/gen/image/WzI1LDE0LHsiZiI6IjJESXRlbXMvQ3VycmVuY3kvSGFydmVzdC9QcmltYWxMaWZlZm9yY2UiLCJzY2FsZSI6MX1d/c498cdfd7f/PrimalLifeforce.png","category":"Currency","detailsId":"primal-crystallised-lifeforce"},{"id":"redeemers-exalted-orb","name":"Redeemer's Exalted Orb","image":"/gen/image/WzI1LDE0LHsiZiI6IjJESXRlbXMvQ3VycmVuY3kvSW5mbHVlbmNlIEV4YWx0cy9FeXJpZU9yYiIsInNjYWxlIjoxfV0/8ec9b52d65/EyrieOrb.png","category":"Currency","detailsId":"redeemers-exalted-orb"},{"id":"reflecting-mist","name":"Reflecting Mist","image":"/gen/image/WzI1LDE0LHsiZiI6IjJESXRlbXMvQ3VycmVuY3kvUmVmbGVjdGl2ZU1pc3QiLCJzY2FsZSI6MX1d/26956f795e/ReflectiveMist.png","category":"Currency","detailsId":"reflecting-mist"},{"id":"regal","name":"Regal Orb","image":"/gen/image/WzI1LDE0LHsiZiI6IjJESXRlbXMvQ3VycmVuY3kvQ3VycmVuY3lVcGdyYWRlTWFnaWNUb1JhcmUiLCJzY2FsZSI6MX1d/0ded706f57/CurrencyUpgradeMagicToRare.png","category":"Currency","detailsId":"regal-orb"},{"id":"regret","name":"Orb of Regret","image":"/gen/image/WzI1LDE0LHsiZiI6IjJESXRlbXMvQ3VycmVuY3kvQ3VycmVuY3lQYXNzaXZlU2tpbGxSZWZ1bmQiLCJzY2FsZSI6MX1d/32d499f562/CurrencyPassiveSkillRefund.png","category":"Currency","detailsId":"orb-of-regret"},{"id":"sacred-lifeforce","name":"Sacred Crystallised Lifeforce","image":"/gen/image/WzI1LDE0LHsiZiI6IjJESXRlbXMvQ3VycmVuY3kvSGFydmVzdC9TYWNyZWRMaWZlZm9yY2UiLCJzY2FsZSI6MX1d/edfba3c893/SacredLifeforce.png","category":"Currency","detailsId":"sacred-crystallised-lifeforce"},{"id":"sandswept-lifeforce","name":"Crystallised Rancour","image":"/gen/image/WzI1LDE0LHsiZiI6IjJESXRlbXMvQ3VycmVuY3kvSGFydmVzdC9GYXJpZHVuTGlmZWZvcmNlIiwic2NhbGUiOjF9XQ/8852b4c459/FaridunLifeforce.png","category":"Currency","detailsId":"crystallised-rancour"},{"id":"scour","name":"Orb of Scouring","image":"/gen/image/WzI1LDE0LHsiZiI6IjJESXRlbXMvQ3VycmVuY3kvQ3VycmVuY3lDb252ZXJ0VG9Ob3JtYWwiLCJzY2FsZSI6MX1d/a0981d67fe/CurrencyConvertToNormal.png","category":"Currency","detailsId":"orb-of-scouring"},{"id":"scrap","name":"Armourer's Scrap","image":"/gen/image/WzI1LDE0LHsiZiI6IjJESXRlbXMvQ3VycmVuY3kvQ3VycmVuY3lBcm1vdXJRdWFsaXR5Iiwic2NhbGUiOjF9XQ/fc4e26afbc/CurrencyArmourQuality.png","category":"Currency","detailsId":"armourers-scrap"},{"id":"shapers-exalted-orb","name":"Shaper's Exalted Orb","image":"/gen/image/WzI1LDE0LHsiZiI6IjJESXRlbXMvQ3VycmVuY3kvU2VjcmV0c29mdGhlQXRsYXMvU2hhcGVyRXhhbHRlZE9yYiIsInNjYWxlIjoxfV0/a8cac8676e/ShaperExaltedOrb.png","category":"Currency","detailsId":"shapers-exalted-orb"},{"id":"tainted-blacksmiths-whetstone","name":"Tainted Blacksmith's Whetstone","image":"/gen/image/WzI1LDE0LHsiZiI6IjJESXRlbXMvQ3VycmVuY3kvSGVsbHNjYXBlL0hlbGxzY2FwZUJsYWNrc21pdGhXaGV0c3RvbmUiLCJzY2FsZSI6MX1d/0309648ccb/HellscapeBlacksmithWhetstone.png","category":"Currency","detailsId":"tainted-blacksmiths-whetstone"},{"id":"tainted-exalted-orb","name":"Tainted Exalted Orb","image":"/gen/image/WzI1LDE0LHsiZiI6IjJESXRlbXMvQ3VycmVuY3kvSGVsbHNjYXBlL0hlbGxzY2FwZUV4YWx0ZWRPcmIiLCJzY2FsZSI6MX1d/68a0ea3020/HellscapeExaltedOrb.png","category":"Currency","detailsId":"tainted-exalted-orb"},{"id":"tainted-orb-of-fusing","name":"Tainted Orb of Fusing","image":"/gen/image/WzI1LDE0LHsiZiI6IjJESXRlbXMvQ3VycmVuY3kvSGVsbHNjYXBlL0hlbGxzY2FwZU9yYk9mRnVzaW5nIiwic2NhbGUiOjF9XQ/845f3c20ed/HellscapeOrbOfFusing.png","category":"Currency","detailsId":"tainted-orb-of-fusing"},{"id":"tempering-catalyst","name":"Tempering Catalyst","image":"/gen/image/WzI1LDE0LHsiZiI6IjJESXRlbXMvQ3VycmVuY3kvQ2F0YWx5c3RzL1RlbXBlcmluZ0NhdGFseXN0Iiwic2NhbGUiOjF9XQ/6bf69c356e/TemperingCatalyst.png","category":"Catalysts","detailsId":"tempering-catalyst"},{"id":"turbulent-catalyst","name":"Turbulent Catalyst","image":"/gen/image/WzI1LDE0LHsiZiI6IjJESXRlbXMvQ3VycmVuY3kvQ2F0YWx5c3RzL1R1cmJ1bGVudENhdGFseXN0Iiwic2NhbGUiOjF9XQ/1f49d03e58/TurbulentCatalyst.png","category":"Catalysts","detailsId":"turbulent-catalyst"},{"id":"veiled-exalted-orb","name":"Veiled Exalted Orb","image":"/gen/image/WzI1LDE0LHsiZiI6IjJESXRlbXMvQ3VycmVuY3kvVmVpbGVkRXhhbHRlZE9yYiIsInNjYWxlIjoxfV0/976e8acb0b/VeiledExaltedOrb.png","category":"Currency","detailsId":"veiled-exalted-orb"},{"id":"vivid-lifeforce","name":"Vivid Crystallised Lifeforce","image":"/gen/image/WzI1LDE0LHsiZiI6IjJESXRlbXMvQ3VycmVuY3kvSGFydmVzdC9WaXZpZExpZmVmb3JjZSIsInNjYWxlIjoxfV0/a355b8a5a2/VividLifeforce.png","category":"Currency","detailsId":"vivid-crystallised-lifeforce"},{"id":"wild-lifeforce","name":"Wild Crystallised Lifeforce","image":"/gen/image/WzI1LDE0LHsiZiI6IjJESXRlbXMvQ3VycmVuY3kvSGFydmVzdC9XaWxkTGlmZWZvcmNlIiwic2NhbGUiOjF9XQ/e3d0b372b0/WildLifeforce.png","category":"Currency","detailsId":"wild-crystallised-lifeforce"},{"id":"chrome","name":"Chromatic Orb","image":"/gen/image/WzI1LDE0LHsiZiI6IjJESXRlbXMvQ3VycmVuY3kvQ3VycmVuY3lSZXJvbGxTb2NrZXRDb2xvdXJzIiwic2NhbGUiOjF9XQ/19c8ddae20/CurrencyRerollSocketColours.png","category":"Currency","detailsId":"chromatic-orb"},{"id":"cluster-fog","name":"Refracting Fog","image":"/gen/image/WzI1LDE0LHsiZiI6IjJESXRlbXMvQ3VycmVuY3kvRGVsaXJpdW0iLCJzY2FsZSI6MX1d/e343b7ca20/Delirium.png","category":"Currency","detailsId":"refracting-fog"},{"id":"crusaders-exalted-orb","name":"Crusader's Exalted Orb","image":"/gen/image/WzI1LDE0LHsiZiI6IjJESXRlbXMvQ3VycmVuY3kvSW5mbHVlbmNlIEV4YWx0cy9DcnVzYWRlck9yYiIsInNjYWxlIjoxfV0/8b48230188/CrusaderOrb.png","category":"Currency","detailsId":"crusaders-exalted-orb"},{"id":"dextral-catalyst","name":"Dextral Catalyst","image":"/gen/image/WzI1LDE0LHsiZiI6IjJESXRlbXMvQ3VycmVuY3kvQ2F0YWx5c3RzL1F1YWxpdHlTdWZmaXhDYXRhbHlzdCIsInNjYWxlIjoxfV0/e38f82e21d/QualitySuffixCatalyst.png","category":"Catalysts","detailsId":"dextral-catalyst"},{"id":"hinekoras-lock","name":"Hinekora's Lock","image":"/gen/image/WzI1LDE0LHsiZiI6IjJESXRlbXMvQ3VycmVuY3kvSGluZWtvcmFzTG9jayIsInNjYWxlIjoxfV0/b188026e7f/HinekorasLock.png","category":"Currency","detailsId":"hinekoras-lock"},{"id":"exceptional-eldritch-ember","name":"Exceptional Eldritch Ember","image":"/gen/image/WzI1LDE0LHsiZiI6IjJESXRlbXMvQ3VycmVuY3kvQ2xlYW5zaW5nRmlyZU9yYlJhbms0Iiwic2NhbGUiOjF9XQ/c2c828fa16/CleansingFireOrbRank4.png","category":"Currency","detailsId":"exceptional-eldritch-ember"},{"id":"foulborn-exalted-orb","name":"Foulborn Exalted Orb","image":"/gen/image/WzI1LDE0LHsiZiI6IjJESXRlbXMvQ3VycmVuY3kvQ2hheXVsYS9Gb3VsYm9ybkV4YWx0ZWQiLCJzY2FsZSI6MX1d/e2146eb9af/FoulbornExalted.png","category":"Keepers","detailsId":"foulborn-exalted-orb"},{"id":"foulborn-orb-of-augmentation","name":"Foulborn Orb of Augmentation","image":"/gen/image/WzI1LDE0LHsiZiI6IjJESXRlbXMvQ3VycmVuY3kvQ2hheXVsYS9Gb3VsYm9ybkF1Z21lbnRhdGlvbiIsInNjYWxlIjoxfV0/44a866f879/FoulbornAugmentation.png","category":"Keepers","detailsId":"foulborn-orb-of-augmentation"},{"id":"foulborn-regal-orb","name":"Foulborn Regal Orb","image":"/gen/image/WzI1LDE0LHsiZiI6IjJESXRlbXMvQ3VycmVuY3kvQ2hheXVsYS9Gb3VsYm9yblJlZ2FsIiwic2NhbGUiOjF9XQ/9226ef718f/FoulbornRegal.png","category":"Keepers","detailsId":"foulborn-regal-orb"},{"id":"gcp","name":"Gemcutter's Prism","image":"/gen/image/WzI1LDE0LHsiZiI6IjJESXRlbXMvQ3VycmVuY3kvQ3VycmVuY3lHZW1RdWFsaXR5Iiwic2NhbGUiOjF9XQ/dbe9678a28/CurrencyGemQuality.png","category":"Currency","detailsId":"gemcutters-prism"},{"id":"hunters-exalted-orb","name":"Hunter's Exalted Orb","image":"/gen/image/WzI1LDE0LHsiZiI6IjJESXRlbXMvQ3VycmVuY3kvSW5mbHVlbmNlIEV4YWx0cy9CYXNpbGlza09yYiIsInNjYWxlIjoxfV0/cd2131d564/BasiliskOrb.png","category":"Currency","detailsId":"hunters-exalted-orb"},{"id":"mavens-chisel-of-divination","name":"Maven's Chisel of Divination","image":"/gen/image/WzI1LDE0LHsiZiI6IjJESXRlbXMvQ3VycmVuY3kvTWF2ZW5DaGlzZWw1Iiwic2NhbGUiOjF9XQ/ff3e7f02eb/MavenChisel5.png","category":"Currency","detailsId":"mavens-chisel-of-divination"},{"id":"mavens-chisel-of-procurement","name":"Maven's Chisel of Procurement","image":"/gen/image/WzI1LDE0LHsiZiI6IjJESXRlbXMvQ3VycmVuY3kvTWF2ZW5DaGlzZWwxIiwic2NhbGUiOjF9XQ/a21d7d73da/MavenChisel1.png","category":"Currency","detailsId":"mavens-chisel-of-procurement"},{"id":"mavens-chisel-of-proliferation","name":"Maven's Chisel of Proliferation","image":"/gen/image/WzI1LDE0LHsiZiI6IjJESXRlbXMvQ3VycmVuY3kvTWF2ZW5DaGlzZWwyIiwic2NhbGUiOjF9XQ/bb82bb4150/MavenChisel2.png","category":"Currency","detailsId":"mavens-chisel-of-proliferation"},{"id":"mavens-orb","name":"Orb of Dominance","image":"/gen/image/WzI1LDE0LHsiZiI6IjJESXRlbXMvQ3VycmVuY3kvTWF2ZW5PcmIiLCJzY2FsZSI6MX1d/f307d80bfd/MavenOrb.png","category":"Currency","detailsId":"orb-of-dominance"},{"id":"mirror","name":"Mirror of Kalandra","image":"/gen/image/WzI1LDE0LHsiZiI6IjJESXRlbXMvQ3VycmVuY3kvQ3VycmVuY3lEdXBsaWNhdGUiLCJzY2FsZSI6MX1d/8d7fea29d1/CurrencyDuplicate.png","category":"Currency","detailsId":"mirror-of-kalandra"},{"id":"mirror-shard","name":"Mirror Shard","image":"/gen/image/WzI1LDE0LHsiZiI6IjJESXRlbXMvQ3VycmVuY3kvTWlycm9yU2hhcmQiLCJzY2FsZSI6MX1d/698183ea2b/MirrorShard.png","category":"Currency","detailsId":"mirror-shard"},{"id":"noxious-catalyst","name":"Noxious Catalyst","image":"/gen/image/WzI1LDE0LHsiZiI6IjJESXRlbXMvQ3VycmVuY3kvQ2F0YWx5c3RzL0NoYW9zUGh5c2ljYWxDYXRhbHlzdCIsInNjYWxlIjoxfV0/2b886f8343/ChaosPhysicalCatalyst.png","category":"Catalysts","detailsId":"noxious-catalyst"},{"id":"portal","name":"Portal Scroll","image":"/gen/image/WzI1LDE0LHsiZiI6IjJESXRlbXMvQ3VycmVuY3kvQ3VycmVuY3lQb3J0YWwiLCJzY2FsZSI6MX1d/d92d3478a0/CurrencyPortal.png","category":"Currency","detailsId":"portal-scroll"},{"id":"prismatic-catalyst","name":"Prismatic Catalyst","image":"/gen/image/WzI1LDE0LHsiZiI6IjJESXRlbXMvQ3VycmVuY3kvQ2F0YWx5c3RzL1ByaXNtYXRpY0NhdGFseXN0Iiwic2NhbGUiOjF9XQ/1e725fd26d/PrismaticCatalyst.png","category":"Catalysts","detailsId":"prismatic-catalyst"},{"id":"rogues-marker","name":"Rogue's Marker","image":"/gen/image/WzI1LDE0LHsiZiI6IjJESXRlbXMvQ3VycmVuY3kvSGVpc3QvSGVpc3RDb2luQ3VycmVuY3kiLCJzY2FsZSI6MX1d/335e66630d/HeistCoinCurrency.png","category":"Currency","detailsId":"rogues-marker"},{"id":"sacred-orb","name":"Sacred Orb","image":"/gen/image/WzI1LDE0LHsiZiI6IjJESXRlbXMvQ3VycmVuY3kvU2FjcmVkT3JiIiwic2NhbGUiOjF9XQ/0380fd0dba/SacredOrb.png","category":"Currency","detailsId":"sacred-orb"},{"id":"sinistral-catalyst","name":"Sinistral Catalyst","image":"/gen/image/WzI1LDE0LHsiZiI6IjJESXRlbXMvQ3VycmVuY3kvQ2F0YWx5c3RzL1F1YWxpdHlQcmVmaXhDYXRhbHlzdCIsInNjYWxlIjoxfV0/0a6b5dfbf8/QualityPrefixCatalyst.png","category":"Catalysts","detailsId":"sinistral-catalyst"},{"id":"stacked-deck","name":"Stacked Deck","image":"/gen/image/WzI1LDE0LHsiZiI6IjJESXRlbXMvRGl2aW5hdGlvbi9EZWNrIiwic2NhbGUiOjF9XQ/8e83aea79a/Deck.png","category":"Currency","detailsId":"stacked-deck"},{"id":"tailoring-orb","name":"Tailoring Orb","image":"/gen/image/WzI1LDE0LHsiZiI6IjJESXRlbXMvQ3VycmVuY3kvRGl2aW5lRW5jaGFudFdlYXBvbkN1cnJlbmN5Iiwic2NhbGUiOjF9XQ/d417654a23/DivineEnchantWeaponCurrency.png","category":"Currency","detailsId":"tailoring-orb"},{"id":"tainted-armourers-scrap","name":"Tainted Armourer's Scrap","image":"/gen/image/WzI1LDE0LHsiZiI6IjJESXRlbXMvQ3VycmVuY3kvSGVsbHNjYXBlL0hlbGxzY2FwZUFybW91cmVyc1NjcmFwIiwic2NhbGUiOjF9XQ/9ee0a10625/HellscapeArmourersScrap.png","category":"Currency","detailsId":"tainted-armourers-scrap"},{"id":"tainted-catalyst","name":"Tainted Catalyst","image":"/gen/image/WzI1LDE0LHsiZiI6IjJESXRlbXMvQ3VycmVuY3kvQ2F0YWx5c3RzL1RhaW50ZWRDYXRhbHlzdCIsInNjYWxlIjoxfV0/5ce364bd70/TaintedCatalyst.png","category":"Catalysts","detailsId":"tainted-catalyst"},{"id":"tainted-chaos-orb","name":"Tainted Chaos Orb","image":"/gen/image/WzI1LDE0LHsiZiI6IjJESXRlbXMvQ3VycmVuY3kvSGVsbHNjYXBlL0hlbGxzY2FwZUNoYW9zT3JiIiwic2NhbGUiOjF9XQ/64d1f4db99/HellscapeChaosOrb.png","category":"Currency","detailsId":"tainted-chaos-orb"},{"id":"tainted-chromatic-orb","name":"Tainted Chromatic Orb","image":"/gen/image/WzI1LDE0LHsiZiI6IjJESXRlbXMvQ3VycmVuY3kvSGVsbHNjYXBlL0hlbGxzY2FwZUNocm9tYXRpY09yYiIsInNjYWxlIjoxfV0/702d29c7ab/HellscapeChromaticOrb.png","category":"Currency","detailsId":"tainted-chromatic-orb"},{"id":"tainted-divine-orb","name":"Volatile Vaal Orb","image":"/gen/image/WzI1LDE0LHsiZiI6IjJESXRlbXMvQ3VycmVuY3kvVm9sYXRpbGVWYWFsT3JiIiwic2NhbGUiOjF9XQ/9bcdda2c63/VolatileVaalOrb.png","category":"Currency","detailsId":"volatile-vaal-orb"},{"id":"tainted-divine-teardrop","name":"Tainted Divine Teardrop","image":"/gen/image/WzI1LDE0LHsiZiI6IjJESXRlbXMvQ3VycmVuY3kvSGVsbHNjYXBlL0hlbGxzY2FwZVRlYXJkcm9wT3JiIiwic2NhbGUiOjF9XQ/0d251b9d52/HellscapeTeardropOrb.png","category":"Currency","detailsId":"tainted-divine-teardrop"},{"id":"tainted-jewellers-orb","name":"Tainted Jeweller's Orb","image":"/gen/image/WzI1LDE0LHsiZiI6IjJESXRlbXMvQ3VycmVuY3kvSGVsbHNjYXBlL0hlbGxzY2FwZUpld2VsbGVyc09yYiIsInNjYWxlIjoxfV0/f146c29db2/HellscapeJewellersOrb.png","category":"Currency","detailsId":"tainted-jewellers-orb"},{"id":"tainted-mythic-orb","name":"Tainted Mythic Orb","image":"/gen/image/WzI1LDE0LHsiZiI6IjJESXRlbXMvQ3VycmVuY3kvSGVsbHNjYXBlL0hlbGxzY2FwZU15dGhpY09yYiIsInNjYWxlIjoxfV0/72ba97d1a8/HellscapeMythicOrb.png","category":"Currency","detailsId":"tainted-mythic-orb"},{"id":"tempering-orb","name":"Tempering Orb","image":"/gen/image/WzI1LDE0LHsiZiI6IjJESXRlbXMvQ3VycmVuY3kvRGl2aW5lRW5jaGFudEJvZHlBcm1vdXJDdXJyZW5jeSIsInNjYWxlIjoxfV0/37681eda1c/DivineEnchantBodyArmourCurrency.png","category":"Currency","detailsId":"tempering-orb"},{"id":"transmute","name":"Orb of Transmutation","image":"/gen/image/WzI1LDE0LHsiZiI6IjJESXRlbXMvQ3VycmVuY3kvQ3VycmVuY3lVcGdyYWRlVG9NYWdpYyIsInNjYWxlIjoxfV0/ded9e8ee63/CurrencyUpgradeToMagic.png","category":"Currency","detailsId":"orb-of-transmutation"},{"id":"unstable-catalyst","name":"Unstable Catalyst","image":"/gen/image/WzI1LDE0LHsiZiI6IjJESXRlbXMvQ3VycmVuY3kvQ2F0YWx5c3RzL0NyaXRpY2FsTW9kaWZpZXJDYXRhbHlzdCIsInNjYWxlIjoxfV0/eebe548a38/CriticalModifierCatalyst.png","category":"Catalysts","detailsId":"unstable-catalyst"},{"id":"vaal","name":"Vaal Orb","image":"/gen/image/WzI1LDE0LHsiZiI6IjJESXRlbXMvQ3VycmVuY3kvQ3VycmVuY3lWYWFsIiwic2NhbGUiOjF9XQ/593fe2e22e/CurrencyVaal.png","category":"Currency","detailsId":"vaal-orb"},{"id":"veiled-chaos-orb","name":"Veiled Chaos Orb","image":"/gen/image/WzI1LDE0LHsiZiI6IjJESXRlbXMvQ3VycmVuY3kvVmVpbGVkQ2hhb3NPcmIiLCJzY2FsZSI6MX1d/fd913b89d0/VeiledChaosOrb.png","category":"Currency","detailsId":"veiled-chaos-orb"},{"id":"warlords-exalted-orb","name":"Warlord's Exalted Orb","image":"/gen/image/WzI1LDE0LHsiZiI6IjJESXRlbXMvQ3VycmVuY3kvSW5mbHVlbmNlIEV4YWx0cy9Db25xdWVyb3JPcmIiLCJzY2FsZSI6MX1d/57f0d85951/ConquerorOrb.png","category":"Currency","detailsId":"warlords-exalted-orb"},{"id":"whetstone","name":"Blacksmith's Whetstone","image":"/gen/image/WzI1LDE0LHsiZiI6IjJESXRlbXMvQ3VycmVuY3kvQ3VycmVuY3lXZWFwb25RdWFsaXR5Iiwic2NhbGUiOjF9XQ/c9cd72719e/CurrencyWeaponQuality.png","category":"Currency","detailsId":"blacksmiths-whetstone"},{"id":"wisdom","name":"Scroll of Wisdom","image":"/gen/image/WzI1LDE0LHsiZiI6IjJESXRlbXMvQ3VycmVuY3kvQ3VycmVuY3lJZGVudGlmaWNhdGlvbiIsInNjYWxlIjoxfV0/c2d03ed3fd/CurrencyIdentification.png","category":"Currency","detailsId":"scroll-of-wisdom"}]}