{"modified":1774234260,"core":{"items":[{"id":"chaos","name":"Chaos Orb","image":"/gen/image/WzI1LDE0LHsiZiI6IjJESXRlbXMvQ3VycmVuY3kvQ3VycmVuY3lSZXJvbGxSYXJlIiwic2NhbGUiOjF9XQ/46a2347805/CurrencyRerollRare.png","category":"Currency","detailsId":"chaos-orb"},{"id":"divine","name":"Divine Orb","image":"/gen/image/WzI1LDE0LHsiZiI6IjJESXRlbXMvQ3VycmVuY3kvQ3VycmVuY3lNb2RWYWx1ZXMiLCJzY2FsZSI6MX1d/ec48896769/CurrencyModValues.png","category":"Currency","detailsId":"divine-orb"}],"rates":{"divine":0.003693},"primary":"chaos","secondary":"divine"},"lines":[{"id":"an-audience-with-the-king","primaryValue":27.78,"volumePrimaryValue":77281,"maxVolumeCurrency":"chaos","maxVolumeRate":0.03600,"sparkline":{"totalChange":-0.47,"data":[-19.06,-7.51,-21.59,-10.22,-4.01,-8.38,-0.47]}},{"id":"awakening-fragment","primaryValue":1.98,"volumePrimaryValue":10610,"maxVolumeCurrency":"chaos","maxVolumeRate":0.5041,"sparkline":{"totalChange":-21.52,"data":[-7.52,-20.95,22.87,-36.03,-28.75,-11.62,-21.52]}},{"id":"barans-crest","primaryValue":4.69,"volumePrimaryValue":5132,"maxVolumeCurrency":"chaos","maxVolumeRate":0.2134,"sparkline":{"totalChange":14.69,"data":[10.82,36.15,41.53,9.64,47.77,41.29,14.69]}},{"id":"al-hezmins-crest","primaryValue":4.08,"volumePrimaryValue":4281,"maxVolumeCurrency":"chaos","maxVolumeRate":0.2451,"sparkline":{"totalChange":7.42,"data":[9.72,-0.72,10.42,7.90,39.51,45.38,7.42]}},{"id":"blazing-fragment","primaryValue":41.43,"volumePrimaryValue":172569,"maxVolumeCurrency":"chaos","maxVolumeRate":0.02414,"sparkline":{"totalChange":33.91,"data":[14.96,-2.28,-6.35,7.97,34.80,50.71,33.91]}},{"id":"chimer","primaryValue":24.08,"volumePrimaryValue":18334,"maxVolumeCurrency":"chaos","maxVolumeRate":0.04152,"sparkline":{"totalChange":9.69,"data":[-14.47,-36.74,-31.92,-24.75,-30.08,-22.08,9.69]}},{"id":"cosmic-fragment","primaryValue":78.15,"volumePrimaryValue":72458,"maxVolumeCurrency":"chaos","maxVolumeRate":0.01280,"sparkline":{"totalChange":-16.41,"data":[18.23,3.80,7.18,6.70,-0.83,-10.90,-16.41]}},{"id":"crescent-splinter","primaryValue":2.43,"volumePrimaryValue":2070,"maxVolumeCurrency":"chaos","maxVolumeRate":0.4110,"sparkline":{"totalChange":-18.40,"data":[-11.01,-12.69,-13.80,-1.79,6.32,-11.32,-18.40]}},{"id":"decaying-fragment","primaryValue":99.20,"volumePrimaryValue":444404,"maxVolumeCurrency":"chaos","maxVolumeRate":0.01008,"sparkline":{"totalChange":-1.47,"data":[2.83,-2.50,4.57,-0.55,1.71,4.24,-1.47]}},{"id":"divine-vessel","primaryValue":0.2191,"volumePrimaryValue":179.8,"maxVolumeCurrency":"chaos","maxVolumeRate":4.56,"sparkline":{"totalChange":-33.99,"data":[-29.88,-39.16,-48.10,-53.91,-40.83,-43.28,-33.99]}},{"id":"droxs-crest","primaryValue":4.84,"volumePrimaryValue":5228,"maxVolumeCurrency":"chaos","maxVolumeRate":0.2067,"sparkline":{"totalChange":11.34,"data":[9.65,0.02,-5.20,-4.28,12.63,35.67,11.34]}},{"id":"dusk","primaryValue":0.2351,"volumePrimaryValue":2903,"maxVolumeCurrency":"chaos","maxVolumeRate":4.25,"sparkline":{"totalChange":-18.73,"data":[12.87,0.17,-21.27,-31.88,-44.12,-37.69,-18.73]}},{"id":"echo-of-loneliness","primaryValue":94.37,"volumePrimaryValue":19864,"maxVolumeCurrency":"chaos","maxVolumeRate":0.01060,"sparkline":{"totalChange":-0.92,"data":[12.82,23.70,-6.89,-10.25,1.57,5.03,-0.92]}},{"id":"fragment-of-constriction","primaryValue":25.26,"volumePrimaryValue":17841,"maxVolumeCurrency":"chaos","maxVolumeRate":0.03958,"sparkline":{"totalChange":-21.22,"data":[-21.33,-34.13,-37.93,-34.77,-35.13,-35.96,-21.22]}},{"id":"fragment-of-emptiness","primaryValue":30.01,"volumePrimaryValue":17583,"maxVolumeCurrency":"chaos","maxVolumeRate":0.03332,"sparkline":{"totalChange":-43.78,"data":[-10.88,-27.19,-26.07,-39.21,-44.44,-44.89,-43.78]}},{"id":"fragment-of-enslavement","primaryValue":21.16,"volumePrimaryValue":15328,"maxVolumeCurrency":"chaos","maxVolumeRate":0.04726,"sparkline":{"totalChange":-31.51,"data":[-18.82,-33.78,-34.49,-34.91,-35.71,-40.44,-31.51]}},{"id":"fragment-of-eradication","primaryValue":22.00,"volumePrimaryValue":15729,"maxVolumeCurrency":"chaos","maxVolumeRate":0.04545,"sparkline":{"totalChange":-33.30,"data":[-21.48,-34.38,-33.53,-33.63,-35.49,-42.48,-33.30]}},{"id":"fragment-of-knowledge","primaryValue":133.5,"volumePrimaryValue":75244,"maxVolumeCurrency":"chaos","maxVolumeRate":0.007489,"sparkline":{"totalChange":-9.15,"data":[-6.48,-12.62,-17.17,-13.20,-5.89,-13.30,-9.15]}},{"id":"fragment-of-purification","primaryValue":19.54,"volumePrimaryValue":13599,"maxVolumeCurrency":"chaos","maxVolumeRate":0.05117,"sparkline":{"totalChange":-39.28,"data":[-20.06,-36.83,-29.40,-12.42,-36.34,-39.13,-39.28]}},{"id":"fragment-of-shape","primaryValue":149.6,"volumePrimaryValue":81138,"maxVolumeCurrency":"chaos","maxVolumeRate":0.006686,"sparkline":{"totalChange":6.19,"data":[3.98,-9.08,-15.62,-0.20,-2.17,1.90,6.19]}},{"id":"grie","primaryValue":4.42,"volumePrimaryValue":19275,"maxVolumeCurrency":"chaos","maxVolumeRate":0.2261,"sparkline":{"totalChange":7.48,"data":[15.39,6.16,-4.33,-5.75,-8.40,-3.24,7.48]}},{"id":"hivebrain-gland","primaryValue":2.39,"volumePrimaryValue":5096,"maxVolumeCurrency":"chaos","maxVolumeRate":0.4183,"sparkline":{"totalChange":-35.87,"data":[3.67,-4.53,-29.37,-30.60,-35.86,-38.87,-35.87]}},{"id":"hydra","primaryValue":22.20,"volumePrimaryValue":17324,"maxVolumeCurrency":"chaos","maxVolumeRate":0.04504,"sparkline":{"totalChange":21.03,"data":[-12.55,-27.75,-23.24,-24.74,-24.91,-19.99,21.03]}},{"id":"ign","primaryValue":5.28,"volumePrimaryValue":11548,"maxVolumeCurrency":"chaos","maxVolumeRate":0.1895,"sparkline":{"totalChange":13.13,"data":[19.94,10.99,-3.42,-10.42,-1.29,19.85,13.13]}},{"id":"memory-of-loneliness","primaryValue":2.06,"volumePrimaryValue":556.5,"maxVolumeCurrency":"chaos","maxVolumeRate":0.4843,"sparkline":{"totalChange":21.80,"data":[82.54,164.6,85.59,38.46,61.02,61.35,21.80]}},{"id":"mid","primaryValue":1.50,"volumePrimaryValue":6504,"maxVolumeCurrency":"chaos","maxVolumeRate":0.6660,"sparkline":{"totalChange":-30.08,"data":[-5.03,-10.05,-14.22,-12.63,-19.49,-30.73,-30.08]}},{"id":"noon","primaryValue":0.7200,"volumePrimaryValue":4711,"maxVolumeCurrency":"chaos","maxVolumeRate":1.39,"sparkline":{"totalChange":-43.23,"data":[-11.45,-18.22,-30.04,-28.15,-45.10,-45.55,-43.23]}},{"id":"offer-dedication","primaryValue":22.88,"volumePrimaryValue":1598,"maxVolumeCurrency":"chaos","maxVolumeRate":0.04371,"sparkline":{"totalChange":-43.13,"data":[17.59,64.63,5.12,-14.25,-26.29,-16.19,-43.13]}},{"id":"ritual-splinter","primaryValue":0.1377,"volumePrimaryValue":93.33,"maxVolumeCurrency":"chaos","maxVolumeRate":7.26,"sparkline":{"totalChange":42.31,"data":[47.50,76.86,41.54,71.07,25.82,20.67,42.31]}},{"id":"ritual-vessel","primaryValue":13.02,"volumePrimaryValue":23729,"maxVolumeCurrency":"chaos","maxVolumeRate":0.07678,"sparkline":{"totalChange":26.32,"data":[73.96,83.93,63.02,37.62,35.86,23.06,26.32]}},{"id":"sacred-blossom","primaryValue":19.49,"volumePrimaryValue":21975,"maxVolumeCurrency":"chaos","maxVolumeRate":0.05131,"sparkline":{"totalChange":0.06,"data":[7.50,5.78,0.53,4.66,6.02,7.13,0.06]}},{"id":"simulacrum","primaryValue":7.32,"volumePrimaryValue":33272,"maxVolumeCurrency":"chaos","maxVolumeRate":0.1366,"sparkline":{"totalChange":-62.88,"data":[-13.50,-35.81,-46.57,-57.77,-62.42,-64.35,-62.88]}},{"id":"syndicate-medallion","primaryValue":1436,"volumePrimaryValue":539534,"maxVolumeCurrency":"divine","maxVolumeRate":0.1886,"sparkline":{"totalChange":36.80,"data":[21.46,28.34,34.44,45.82,48.06,44.79,36.80]}},{"id":"the-mavens-writ","primaryValue":6.00,"volumePrimaryValue":17137,"maxVolumeCurrency":"chaos","maxVolumeRate":0.1668,"sparkline":{"totalChange":-38.10,"data":[-18.74,-18.04,-38.62,-35.07,-44.38,-39.53,-38.10]}},{"id":"timeless-eternal-empire-splinter","primaryValue":0.06211,"volumePrimaryValue":16.67,"maxVolumeCurrency":"chaos","maxVolumeRate":16.1,"sparkline":{"totalChange":26.11,"data":[-27.36,-44.13,-36.06,-24.86,-48.40,-10.44,26.11]}},{"id":"timeless-karui-splinter","primaryValue":0.1801,"volumePrimaryValue":31.33,"maxVolumeCurrency":"chaos","maxVolumeRate":5.55,"sparkline":{"totalChange":-40.41,"data":[10.38,-9.96,14.14,-31.23,-31.53,75.92,-40.41]}},{"id":"timeless-maraketh-emblem","primaryValue":11.75,"volumePrimaryValue":16523,"maxVolumeCurrency":"chaos","maxVolumeRate":0.08508,"sparkline":{"totalChange":113.6,"data":[2.81,-0.45,20.41,92.26,77.64,189.8,113.6]}},{"id":"timeless-maraketh-splinter","primaryValue":0.2077,"volumePrimaryValue":126.0,"maxVolumeCurrency":"chaos","maxVolumeRate":4.81,"sparkline":{"totalChange":-1.98,"data":[30.48,-51.66,-72.22,-40.51,-42.07,5.85,-1.98]}},{"id":"timeless-templar-emblem","primaryValue":43.82,"volumePrimaryValue":57194,"maxVolumeCurrency":"chaos","maxVolumeRate":0.02282,"sparkline":{"totalChange":208.3,"data":[4.33,17.04,43.01,97.45,146.1,216.7,208.3]}},{"id":"timeless-templar-splinter","primaryValue":0.3362,"volumePrimaryValue":437.3,"maxVolumeCurrency":"chaos","maxVolumeRate":2.97,"sparkline":{"totalChange":266.5,"data":[22.40,-57.47,-40.51,0.83,70.76,172.1,266.5]}},{"id":"timeless-vaal-splinter","primaryValue":0.05414,"volumePrimaryValue":22.33,"maxVolumeCurrency":"chaos","maxVolumeRate":18.47,"sparkline":{"totalChange":-28.74,"data":[414.8,254.0,278.4,327.9,325.7,228.2,-28.74]}},{"id":"traumatic-fragment","primaryValue":31.56,"volumePrimaryValue":38522,"maxVolumeCurrency":"chaos","maxVolumeRate":0.03168,"sparkline":{"totalChange":-42.82,"data":[-1.23,-9.97,-33.57,-42.08,-39.73,-42.31,-42.82]}},{"id":"uber-timeless-templar-emblem","primaryValue":89.87,"volumePrimaryValue":4868,"maxVolumeCurrency":"chaos","maxVolumeRate":0.01113,"sparkline":{"totalChange":116.8,"data":[-4.25,-18.77,-16.40,101.2,59.66,117.2,116.8]}},{"id":"valdos-puzzle-box","primaryValue":288.4,"volumePrimaryValue":4596867,"maxVolumeCurrency":"divine","maxVolumeRate":0.9388,"sparkline":{"totalChange":22.21,"data":[9.02,16.86,13.52,14.76,15.55,15.52,22.21]}},{"id":"dawn","primaryValue":0.3199,"volumePrimaryValue":2774,"maxVolumeCurrency":"chaos","maxVolumeRate":3.13,"sparkline":{"totalChange":-31.93,"data":[-7.01,-9.88,-28.74,-28.62,-44.56,-37.12,-31.93]}},{"id":"devouring-fragment","primaryValue":154.3,"volumePrimaryValue":572813,"maxVolumeCurrency":"chaos","maxVolumeRate":0.006480,"sparkline":{"totalChange":0.28,"data":[9.52,6.14,6.01,9.13,9.69,4.40,0.28]}},{"id":"echo-of-reverence","primaryValue":239.1,"volumePrimaryValue":206182,"maxVolumeCurrency":"chaos","maxVolumeRate":0.004182,"sparkline":{"totalChange":6.52,"data":[2.64,-4.07,-7.44,0.43,-1.21,-3.58,6.52]}},{"id":"echo-of-trauma","primaryValue":209.9,"volumePrimaryValue":64031,"maxVolumeCurrency":"chaos","maxVolumeRate":0.004763,"sparkline":{"totalChange":118.9,"data":[12.71,25.58,5.21,30.80,96.55,112.5,118.9]}},{"id":"fragment-of-terror","primaryValue":32.45,"volumePrimaryValue":18076,"maxVolumeCurrency":"chaos","maxVolumeRate":0.03081,"sparkline":{"totalChange":-36.38,"data":[-6.92,-18.87,-29.89,-36.35,-42.59,-43.95,-36.38]}},{"id":"hope","primaryValue":5.80,"volumePrimaryValue":11424,"maxVolumeCurrency":"chaos","maxVolumeRate":0.1724,"sparkline":{"totalChange":-7.83,"data":[9.36,12.71,-10.52,-21.28,-22.42,0.80,-7.83]}},{"id":"lonely-fragment","primaryValue":21.67,"volumePrimaryValue":28721,"maxVolumeCurrency":"chaos","maxVolumeRate":0.04614,"sparkline":{"totalChange":26.58,"data":[28.27,48.55,8.27,-5.35,13.99,22.45,26.58]}},{"id":"memory-of-reverence","primaryValue":24.75,"volumePrimaryValue":29292,"maxVolumeCurrency":"chaos","maxVolumeRate":0.04040,"sparkline":{"totalChange":-32.66,"data":[-13.01,-20.56,-26.93,-26.11,-35.87,-41.64,-32.66]}},{"id":"memory-of-trauma","primaryValue":5.32,"volumePrimaryValue":2146,"maxVolumeCurrency":"chaos","maxVolumeRate":0.1880,"sparkline":{"totalChange":121.8,"data":[-9.61,61.46,62.32,28.72,87.47,84.74,121.8]}},{"id":"minot","primaryValue":7.36,"volumePrimaryValue":6219,"maxVolumeCurrency":"chaos","maxVolumeRate":0.1360,"sparkline":{"totalChange":-24.34,"data":[-2.55,-19.45,-28.31,-43.04,-43.99,-40.77,-24.34]}},{"id":"offer","primaryValue":2.10,"volumePrimaryValue":3216,"maxVolumeCurrency":"chaos","maxVolumeRate":0.4754,"sparkline":{"totalChange":-18.02,"data":[-14.77,-15.54,-26.11,-16.92,-19.97,-9.36,-18.02]}},{"id":"offer-gift","primaryValue":635.6,"volumePrimaryValue":56990,"maxVolumeCurrency":"chaos","maxVolumeRate":0.001573,"sparkline":{"totalChange":3.04,"data":[22.00,-5.81,-11.10,2.02,3.36,8.28,3.04]}},{"id":"offer-tribute","primaryValue":18.78,"volumePrimaryValue":1571,"maxVolumeCurrency":"chaos","maxVolumeRate":0.05325,"sparkline":{"totalChange":-4.15,"data":[21.20,35.34,2.92,3.17,5.16,6.05,-4.15]}},{"id":"phoenix","primaryValue":8.12,"volumePrimaryValue":6563,"maxVolumeCurrency":"chaos","maxVolumeRate":0.1231,"sparkline":{"totalChange":-24.70,"data":[0.62,-26.67,-31.96,-34.93,-30.37,-27.42,-24.70]}},{"id":"rage","primaryValue":4.47,"volumePrimaryValue":13713,"maxVolumeCurrency":"chaos","maxVolumeRate":0.2239,"sparkline":{"totalChange":9.17,"data":[15.28,6.35,-2.07,-5.24,-10.59,5.95,9.17]}},{"id":"reality-fragment","primaryValue":133.8,"volumePrimaryValue":814896,"maxVolumeCurrency":"divine","maxVolumeRate":2.02,"sparkline":{"totalChange":29.62,"data":[14.97,28.78,32.67,32.79,25.63,24.08,29.62]}},{"id":"reverent-fragment","primaryValue":122.5,"volumePrimaryValue":169829,"maxVolumeCurrency":"chaos","maxVolumeRate":0.008162,"sparkline":{"totalChange":3.78,"data":[3.03,1.77,8.40,17.39,5.83,14.29,3.78]}},{"id":"simulacrum-splinter","primaryValue":0.01081,"volumePrimaryValue":108.8,"maxVolumeCurrency":"chaos","maxVolumeRate":92.52,"sparkline":{"totalChange":-71.14,"data":[6.99,4.24,-20.81,-42.23,-53.60,-62.38,-71.14]}},{"id":"synthesising-fragment","primaryValue":9.81,"volumePrimaryValue":46813,"maxVolumeCurrency":"chaos","maxVolumeRate":0.1019,"sparkline":{"totalChange":-20.21,"data":[-25.51,-31.31,-36.84,-35.39,-17.40,-11.00,-20.21]}},{"id":"the-black-barya","primaryValue":373.9,"volumePrimaryValue":2076464,"maxVolumeCurrency":"chaos","maxVolumeRate":0.002674,"sparkline":{"totalChange":16.15,"data":[-4.76,-6.63,-4.37,0.80,5.13,2.94,16.15]}},{"id":"timeless-eternal-emblem","primaryValue":2.97,"volumePrimaryValue":4599,"maxVolumeCurrency":"chaos","maxVolumeRate":0.3365,"sparkline":{"totalChange":97.14,"data":[31.03,20.94,73.91,108.1,101.8,118.3,97.14]}},{"id":"timeless-karui-emblem","primaryValue":2.70,"volumePrimaryValue":4303,"maxVolumeCurrency":"chaos","maxVolumeRate":0.3709,"sparkline":{"totalChange":59.52,"data":[-3.33,-6.77,8.00,52.02,76.95,69.47,59.52]}},{"id":"timeless-vaal-emblem","primaryValue":6.64,"volumePrimaryValue":9758,"maxVolumeCurrency":"chaos","maxVolumeRate":0.1507,"sparkline":{"totalChange":47.71,"data":[-22.66,-21.40,-12.12,4.63,16.12,61.48,47.71]}},{"id":"uber-timeless-eternal-emblem","primaryValue":116.6,"volumePrimaryValue":7056,"maxVolumeCurrency":"chaos","maxVolumeRate":0.008574,"sparkline":{"totalChange":43.71,"data":[-5.02,-20.09,-4.86,32.30,18.23,51.13,43.71]}},{"id":"uber-timeless-karui-emblem","primaryValue":104.6,"volumePrimaryValue":6187,"maxVolumeCurrency":"chaos","maxVolumeRate":0.009564,"sparkline":{"totalChange":82.58,"data":[6.29,18.50,17.91,68.03,56.40,101.3,82.58]}},{"id":"uber-timeless-maraketh-emblem","primaryValue":158.0,"volumePrimaryValue":8372,"maxVolumeCurrency":"chaos","maxVolumeRate":0.006331,"sparkline":{"totalChange":66.61,"data":[-8.86,-34.03,-18.26,9.40,10.70,40.02,66.61]}},{"id":"uber-timeless-vaal-emblem","primaryValue":123.5,"volumePrimaryValue":7391,"maxVolumeCurrency":"chaos","maxVolumeRate":0.008095,"sparkline":{"totalChange":66.58,"data":[-12.69,-11.10,10.55,42.13,24.08,65.31,66.58]}},{"id":"veritanias-crest","primaryValue":5.71,"volumePrimaryValue":6346,"maxVolumeCurrency":"chaos","maxVolumeRate":0.1752,"sparkline":{"totalChange":47.65,"data":[12.31,-3.41,14.99,123.6,56.98,65.84,47.65]}},{"id":"voidborn-reliquary-key","primaryValue":671.8,"volumePrimaryValue":904969,"maxVolumeCurrency":"divine","maxVolumeRate":0.4031,"sparkline":{"totalChange":1.11,"data":[-5.25,-3.87,-3.95,-3.30,-1.39,-5.23,1.11]}}],"items":[{"id":"an-audience-with-the-king","name":"An Audience With The King","image":"/gen/image/WzI1LDE0LHsiZiI6IjJESXRlbXMvQ3VycmVuY3kvQXptZXJpL1Zvb2Rvb0tpbmdFZmZpZ3kiLCJzY2FsZSI6MX1d/55e8fd8f34/VoodooKingEffigy.png","category":"Fragments","detailsId":"an-audience-with-the-king"},{"id":"awakening-fragment","name":"Awakening Fragment","image":"/gen/image/WzI4LDE0LHsiZiI6IjJESXRlbXMvTWFwcy9VYmVyQm9zc0tleVNpcnVzIiwic2NhbGUiOjF9XQ/094681ee85/UberBossKeySirus.png","category":"Fragments","detailsId":"awakening-fragment"},{"id":"barans-crest","name":"Baran's Crest","image":"/gen/image/WzI4LDE0LHsiZiI6IjJESXRlbXMvTWFwcy9DcnVzYWRlckZyYWdtZW50Iiwic2NhbGUiOjF9XQ/3e2fecf3bc/CrusaderFragment.png","category":"Fragments","detailsId":"barans-crest"},{"id":"al-hezmins-crest","name":"Al-Hezmin's Crest","image":"/gen/image/WzI4LDE0LHsiZiI6IjJESXRlbXMvTWFwcy9IdW50ZXJGcmFnbWVudCIsInNjYWxlIjoxfV0/3ad268c533/HunterFragment.png","category":"Fragments","detailsId":"al-hezmins-crest"},{"id":"blazing-fragment","name":"Blazing Fragment","image":"/gen/image/WzI4LDE0LHsiZiI6IjJESXRlbXMvTWFwcy9VYmVyQm9zc0tleVNlYXJpbmdFeGFyY2giLCJzY2FsZSI6MX1d/cc2f3bce1b/UberBossKeySearingExarch.png","category":"Fragments","detailsId":"blazing-fragment"},{"id":"chimer","name":"Fragment of the Chimera","image":"/gen/image/WzI4LDE0LHsiZiI6IjJESXRlbXMvTWFwcy9BdGxhc01hcHMvRnJhZ21lbnRDaGltZXJhIiwic2NhbGUiOjF9XQ/191b838e55/FragmentChimera.png","category":"Fragments","detailsId":"fragment-of-the-chimera"},{"id":"cosmic-fragment","name":"Cosmic Fragment","image":"/gen/image/WzI4LDE0LHsiZiI6IjJESXRlbXMvTWFwcy9VYmVyQm9zc0tleVNoYXBlciIsInNjYWxlIjoxfV0/719e96a82a/UberBossKeyShaper.png","category":"Fragments","detailsId":"cosmic-fragment"},{"id":"crescent-splinter","name":"Crescent Splinter","image":"/gen/image/WzI1LDE0LHsiZiI6IjJESXRlbXMvQ3VycmVuY3kvQXRsYXMvTWF2ZW5LZXlGcmFnbWVudCIsInNjYWxlIjoxfV0/014d46c630/MavenKeyFragment.png","category":"Fragments","detailsId":"crescent-splinter"},{"id":"decaying-fragment","name":"Decaying Fragment","image":"/gen/image/WzI4LDE0LHsiZiI6IjJESXRlbXMvTWFwcy9VYmVyQm9zc0tleUVsZGVyIiwic2NhbGUiOjF9XQ/42d1e96e4e/UberBossKeyElder.png","category":"Fragments","detailsId":"decaying-fragment"},{"id":"divine-vessel","name":"Divine Vessel","image":"/gen/image/WzI4LDE0LHsiZiI6IjJESXRlbXMvTWFwcy9TaW5GbGFza0VtcHR5Iiwic2NhbGUiOjF9XQ/3a2d49608a/SinFlaskEmpty.png","category":"Fragments","detailsId":"divine-vessel"},{"id":"droxs-crest","name":"Drox's Crest","image":"/gen/image/WzI4LDE0LHsiZiI6IjJESXRlbXMvTWFwcy9XYXJsb3JkRnJhZ21lbnQiLCJzY2FsZSI6MX1d/3d735a8303/WarlordFragment.png","category":"Fragments","detailsId":"droxs-crest"},{"id":"dusk","name":"Sacrifice at Dusk","image":"/gen/image/WzI4LDE0LHsiZiI6IjJESXRlbXMvTWFwcy9WYWFsMDQiLCJzY2FsZSI6MX1d/3be8311430/Vaal04.png","category":"Fragments","detailsId":"sacrifice-at-dusk"},{"id":"echo-of-loneliness","name":"Echo of Loneliness","image":"/gen/image/WzI4LDE0LHsiZiI6IjJESXRlbXMvTWFwcy9JZ25vcmFuY2VCb3NzTWVtb3J5S2V5Iiwic2NhbGUiOjF9XQ/f297c3c619/IgnoranceBossMemoryKey.png","category":"Fragments","detailsId":"echo-of-loneliness"},{"id":"fragment-of-constriction","name":"Fragment of Constriction","image":"/gen/image/WzI4LDE0LHsiZiI6IjJESXRlbXMvTWFwcy9BdGxhc01hcEd1YXJkaWFuSG9seSIsInNjYWxlIjoxfV0/b9ef66f983/AtlasMapGuardianHoly.png","category":"Fragments","detailsId":"fragment-of-constriction"},{"id":"fragment-of-emptiness","name":"Fragment of Emptiness","image":"/gen/image/WzI4LDE0LHsiZiI6IjJESXRlbXMvTWFwcy9VYmVyRWxkZXIwMiIsInNjYWxlIjoxfV0/085f7abd0b/UberElder02.png","category":"Fragments","detailsId":"fragment-of-emptiness"},{"id":"fragment-of-enslavement","name":"Fragment of Enslavement","image":"/gen/image/WzI4LDE0LHsiZiI6IjJESXRlbXMvTWFwcy9BdGxhc01hcEd1YXJkaWFuRmlyZSIsInNjYWxlIjoxfV0/7497ffd64d/AtlasMapGuardianFire.png","category":"Fragments","detailsId":"fragment-of-enslavement"},{"id":"fragment-of-eradication","name":"Fragment of Eradication","image":"/gen/image/WzI4LDE0LHsiZiI6IjJESXRlbXMvTWFwcy9BdGxhc01hcEd1YXJkaWFuTGlnaHRuaW5nIiwic2NhbGUiOjF9XQ/e6e792e80e/AtlasMapGuardianLightning.png","category":"Fragments","detailsId":"fragment-of-eradication"},{"id":"fragment-of-knowledge","name":"Fragment of Knowledge","image":"/gen/image/WzI4LDE0LHsiZiI6IjJESXRlbXMvTWFwcy9VYmVyRWxkZXIwNCIsInNjYWxlIjoxfV0/096ec774b0/UberElder04.png","category":"Fragments","detailsId":"fragment-of-knowledge"},{"id":"fragment-of-purification","name":"Fragment of Purification","image":"/gen/image/WzI4LDE0LHsiZiI6IjJESXRlbXMvTWFwcy9BdGxhc01hcEd1YXJkaWFuQ2hhb3MiLCJzY2FsZSI6MX1d/7938e7a7ee/AtlasMapGuardianChaos.png","category":"Fragments","detailsId":"fragment-of-purification"},{"id":"fragment-of-shape","name":"Fragment of Shape","image":"/gen/image/WzI4LDE0LHsiZiI6IjJESXRlbXMvTWFwcy9VYmVyRWxkZXIwMyIsInNjYWxlIjoxfV0/4a8c196777/UberElder03.png","category":"Fragments","detailsId":"fragment-of-shape"},{"id":"grie","name":"Mortal Grief","image":"/gen/image/WzI4LDE0LHsiZiI6IjJESXRlbXMvTWFwcy9VYmVyVmFhbDA0Iiwic2NhbGUiOjF9XQ/fa8dd8fea2/UberVaal04.png","category":"Fragments","detailsId":"mortal-grief"},{"id":"hivebrain-gland","name":"Hivebrain Gland","image":"/gen/image/WzI4LDE0LHsiZiI6IjJESXRlbXMvTWFwcy9Cb3NzS2V5QnJlcXVlbCIsInNjYWxlIjoxfV0/69f4dc2d20/BossKeyBrequel.png","category":"Fragments","detailsId":"hivebrain-gland"},{"id":"hydra","name":"Fragment of the Hydra","image":"/gen/image/WzI4LDE0LHsiZiI6IjJESXRlbXMvTWFwcy9BdGxhc01hcHMvRnJhZ21lbnRIeWRyYSIsInNjYWxlIjoxfV0/975dcd6b1c/FragmentHydra.png","category":"Fragments","detailsId":"fragment-of-the-hydra"},{"id":"ign","name":"Mortal Ignorance","image":"/gen/image/WzI4LDE0LHsiZiI6IjJESXRlbXMvTWFwcy9VYmVyVmFhbDAzIiwic2NhbGUiOjF9XQ/3d126fe51b/UberVaal03.png","category":"Fragments","detailsId":"mortal-ignorance"},{"id":"memory-of-loneliness","name":"Memory of Loneliness","image":"/gen/image/WzI1LDE0LHsiZiI6IjJESXRlbXMvQ3VycmVuY3kvQXRsYXMvTWVtb3J5SW5jYXJuYXRpb25vZk5lZ2xlY3QiLCJzY2FsZSI6MX1d/788219c481/MemoryIncarnationofNeglect.png","category":"Fragments","detailsId":"memory-of-loneliness"},{"id":"mid","name":"Sacrifice at Midnight","image":"/gen/image/WzI4LDE0LHsiZiI6IjJESXRlbXMvTWFwcy9WYWFsMDEiLCJzY2FsZSI6MX1d/c7cd8058f6/Vaal01.png","category":"Fragments","detailsId":"sacrifice-at-midnight"},{"id":"noon","name":"Sacrifice at Noon","image":"/gen/image/WzI4LDE0LHsiZiI6IjJESXRlbXMvTWFwcy9WYWFsMDMiLCJzY2FsZSI6MX1d/55524425f4/Vaal03.png","category":"Fragments","detailsId":"sacrifice-at-noon"},{"id":"offer-dedication","name":"Dedication to the Goddess","image":"/gen/image/WzI4LDE0LHsiZiI6IjJESXRlbXMvTWFwcy9MYWJ5cmludGhIYXJ2ZXN0SW5mdXNlZDIiLCJzY2FsZSI6MX1d/31d582aac1/LabyrinthHarvestInfused2.png","category":"Fragments","detailsId":"dedication-to-the-goddess"},{"id":"ritual-splinter","name":"Ritual Splinter","image":"/gen/image/WzI1LDE0LHsiZiI6IjJESXRlbXMvQ3VycmVuY3kvUml0dWFsL1JpdHVhbFNwbGludGVyIiwic2NhbGUiOjF9XQ/702c7441d8/RitualSplinter.png","category":"Fragments","detailsId":"ritual-splinter"},{"id":"ritual-vessel","name":"Ritual Vessel","image":"/gen/image/WzI1LDE0LHsiZiI6IjJESXRlbXMvQ3VycmVuY3kvUml0dWFsL0VmZmlneSIsInNjYWxlIjoxfV0/1686de4490/Effigy.png","category":"Fragments","detailsId":"ritual-vessel"},{"id":"sacred-blossom","name":"Sacred Blossom","image":"/gen/image/WzI4LDE0LHsiZiI6IjJESXRlbXMvTWFwcy9Pc2hhYmlNYXAiLCJzY2FsZSI6MX1d/ae20ec4d5f/OshabiMap.png","category":"Fragments","detailsId":"sacred-blossom"},{"id":"simulacrum","name":"Simulacrum","image":"/gen/image/WzI4LDE0LHsiZiI6IjJESXRlbXMvTWFwcy9EZWxpcml1bUZyYWdtZW50Iiwic2NhbGUiOjF9XQ/7f29157183/DeliriumFragment.png","category":"Fragments","detailsId":"simulacrum"},{"id":"syndicate-medallion","name":"Syndicate Medallion","image":"/gen/image/WzI4LDE0LHsiZiI6IjJESXRlbXMvTWFwcy9DYXRhcmluYVRva2VuIiwic2NhbGUiOjF9XQ/e8d8cc5155/CatarinaToken.png","category":"Fragments","detailsId":"syndicate-medallion"},{"id":"the-mavens-writ","name":"The Maven's Writ","image":"/gen/image/WzI1LDE0LHsiZiI6IjJESXRlbXMvQ3VycmVuY3kvQXRsYXMvTWF2ZW5LZXkiLCJzY2FsZSI6MX1d/40683e487b/MavenKey.png","category":"Fragments","detailsId":"the-mavens-writ"},{"id":"timeless-eternal-empire-splinter","name":"Timeless Eternal Empire Splinter","image":"/gen/image/WzI4LDE0LHsiZiI6IjJESXRlbXMvTWFwcy9FdGVybmFsRW1waXJlU2hhcmQiLCJzY2FsZSI6MX1d/f404e7925c/EternalEmpireShard.png","category":"Fragments","detailsId":"timeless-eternal-empire-splinter"},{"id":"timeless-karui-splinter","name":"Timeless Karui Splinter","image":"/gen/image/WzI4LDE0LHsiZiI6IjJESXRlbXMvTWFwcy9LYXJ1aVNoYXJkIiwic2NhbGUiOjF9XQ/dd21055148/KaruiShard.png","category":"Fragments","detailsId":"timeless-karui-splinter"},{"id":"timeless-maraketh-emblem","name":"Timeless Maraketh Emblem","image":"/gen/image/WzI4LDE0LHsiZiI6IjJESXRlbXMvTWFwcy9NYXJha2V0aEZyYWdtZW50Iiwic2NhbGUiOjF9XQ/a81c4968ab/MarakethFragment.png","category":"Fragments","detailsId":"timeless-maraketh-emblem"},{"id":"timeless-maraketh-splinter","name":"Timeless Maraketh Splinter","image":"/gen/image/WzI4LDE0LHsiZiI6IjJESXRlbXMvTWFwcy9NYXJha2V0aFNoYXJkIiwic2NhbGUiOjF9XQ/04ec0d80fe/MarakethShard.png","category":"Fragments","detailsId":"timeless-maraketh-splinter"},{"id":"timeless-templar-emblem","name":"Timeless Templar Emblem","image":"/gen/image/WzI4LDE0LHsiZiI6IjJESXRlbXMvTWFwcy9UZW1wbGFyRnJhZ21lbnQiLCJzY2FsZSI6MX1d/e7ede9f816/TemplarFragment.png","category":"Fragments","detailsId":"timeless-templar-emblem"},{"id":"timeless-templar-splinter","name":"Timeless Templar Splinter","image":"/gen/image/WzI4LDE0LHsiZiI6IjJESXRlbXMvTWFwcy9UZW1wbGFyU2hhcmQiLCJzY2FsZSI6MX1d/fd3d766dd5/TemplarShard.png","category":"Fragments","detailsId":"timeless-templar-splinter"},{"id":"timeless-vaal-splinter","name":"Timeless Vaal Splinter","image":"/gen/image/WzI4LDE0LHsiZiI6IjJESXRlbXMvTWFwcy9WYWFsU2hhcmQiLCJzY2FsZSI6MX1d/6b356215ac/VaalShard.png","category":"Fragments","detailsId":"timeless-vaal-splinter"},{"id":"traumatic-fragment","name":"Traumatic Fragment","image":"/gen/image/WzI4LDE0LHsiZiI6IjJESXRlbXMvTWFwcy9VYmVyQm9zc0tleUluY2FybmF0aW9uT2ZGZWFyIiwic2NhbGUiOjF9XQ/cae043624e/UberBossKeyIncarnationOfFear.png","category":"Fragments","detailsId":"traumatic-fragment"},{"id":"uber-timeless-templar-emblem","name":"Unrelenting Timeless Templar Emblem","image":"/gen/image/WzI4LDE0LHsiZiI6IjJESXRlbXMvTWFwcy9UaW1lbGVzc0NvbmZsaWN0VGVtcGxhciIsInNjYWxlIjoxfV0/b0a76a5f78/TimelessConflictTemplar.png","category":"Fragments","detailsId":"unrelenting-timeless-templar-emblem"},{"id":"valdos-puzzle-box","name":"Valdo's Puzzle Box","image":"/gen/image/WzI1LDE0LHsiZiI6IjJESXRlbXMvQ3VycmVuY3kvVmFsZG9zUHV6emxlQm94Iiwic2NhbGUiOjF9XQ/bed9b1b28b/ValdosPuzzleBox.png","category":"Fragments","detailsId":"valdos-puzzle-box"},{"id":"dawn","name":"Sacrifice at Dawn","image":"/gen/image/WzI4LDE0LHsiZiI6IjJESXRlbXMvTWFwcy9WYWFsMDIiLCJzY2FsZSI6MX1d/3516d95235/Vaal02.png","category":"Fragments","detailsId":"sacrifice-at-dawn"},{"id":"devouring-fragment","name":"Devouring Fragment","image":"/gen/image/WzI4LDE0LHsiZiI6IjJESXRlbXMvTWFwcy9VYmVyQm9zc0tleUVhdGVyT2ZXb3JsZHMiLCJzY2FsZSI6MX1d/6022aa0897/UberBossKeyEaterOfWorlds.png","category":"Fragments","detailsId":"devouring-fragment"},{"id":"echo-of-reverence","name":"Echo of Reverence","image":"/gen/image/WzI4LDE0LHsiZiI6IjJESXRlbXMvTWFwcy9CZW5ldm9sZW5jZUJvc3NNZW1vcnlLZXkiLCJzY2FsZSI6MX1d/ca22192d81/BenevolenceBossMemoryKey.png","category":"Fragments","detailsId":"echo-of-reverence"},{"id":"echo-of-trauma","name":"Echo of Trauma","image":"/gen/image/WzI4LDE0LHsiZiI6IjJESXRlbXMvTWFwcy9BbmdlckJvc3NNZW1vcnlLZXkiLCJzY2FsZSI6MX1d/dd51600b23/AngerBossMemoryKey.png","category":"Fragments","detailsId":"echo-of-trauma"},{"id":"fragment-of-terror","name":"Fragment of Terror","image":"/gen/image/WzI4LDE0LHsiZiI6IjJESXRlbXMvTWFwcy9VYmVyRWxkZXIwMSIsInNjYWxlIjoxfV0/322988dd38/UberElder01.png","category":"Fragments","detailsId":"fragment-of-terror"},{"id":"hope","name":"Mortal Hope","image":"/gen/image/WzI4LDE0LHsiZiI6IjJESXRlbXMvTWFwcy9VYmVyVmFhbDAyIiwic2NhbGUiOjF9XQ/9f6c126c9e/UberVaal02.png","category":"Fragments","detailsId":"mortal-hope"},{"id":"lonely-fragment","name":"Lonely Fragment","image":"/gen/image/WzI4LDE0LHsiZiI6IjJESXRlbXMvTWFwcy9VYmVyQm9zc0tleUluY2FybmF0aW9uT2ZOZWdsZWN0Iiwic2NhbGUiOjF9XQ/ae7eaccae3/UberBossKeyIncarnationOfNeglect.png","category":"Fragments","detailsId":"lonely-fragment"},{"id":"memory-of-reverence","name":"Memory of Reverence","image":"/gen/image/WzI1LDE0LHsiZiI6IjJESXRlbXMvQ3VycmVuY3kvQXRsYXMvTWVtb3J5SW5jYXJuYXRpb25vZkRyZWFkIiwic2NhbGUiOjF9XQ/66dedce814/MemoryIncarnationofDread.png","category":"Fragments","detailsId":"memory-of-reverence"},{"id":"memory-of-trauma","name":"Memory of Trauma","image":"/gen/image/WzI1LDE0LHsiZiI6IjJESXRlbXMvQ3VycmVuY3kvQXRsYXMvTWVtb3J5SW5jYXJuYXRpb25vZkZlYXIiLCJzY2FsZSI6MX1d/2d4b1e2bbc/MemoryIncarnationofFear.png","category":"Fragments","detailsId":"memory-of-trauma"},{"id":"minot","name":"Fragment of the Minotaur","image":"/gen/image/WzI4LDE0LHsiZiI6IjJESXRlbXMvTWFwcy9BdGxhc01hcHMvRnJhZ21lbnRNaW5vdGF1ciIsInNjYWxlIjoxfV0/e976236f7a/FragmentMinotaur.png","category":"Fragments","detailsId":"fragment-of-the-minotaur"},{"id":"offer","name":"Offering to the Goddess","image":"/gen/image/WzI4LDE0LHsiZiI6IjJESXRlbXMvTWFwcy9MYWJ5cmludGgiLCJzY2FsZSI6MX1d/24fe6dc261/Labyrinth.png","category":"Fragments","detailsId":"offering-to-the-goddess"},{"id":"offer-gift","name":"Gift to the Goddess","image":"/gen/image/WzI4LDE0LHsiZiI6IjJESXRlbXMvTWFwcy9MYWJ5cmludGhIYXJ2ZXN0SW5mdXNlZDEiLCJzY2FsZSI6MX1d/a5254d7933/LabyrinthHarvestInfused1.png","category":"Fragments","detailsId":"gift-to-the-goddess"},{"id":"offer-tribute","name":"Tribute to the Goddess","image":"/gen/image/WzI4LDE0LHsiZiI6IjJESXRlbXMvTWFwcy9MYWJ5cmludGhIYXJ2ZXN0Iiwic2NhbGUiOjF9XQ/81054ff374/LabyrinthHarvest.png","category":"Fragments","detailsId":"tribute-to-the-goddess"},{"id":"phoenix","name":"Fragment of the Phoenix","image":"/gen/image/WzI4LDE0LHsiZiI6IjJESXRlbXMvTWFwcy9BdGxhc01hcHMvRnJhZ21lbnRQaG9lbml4Iiwic2NhbGUiOjF9XQ/3091d971ad/FragmentPhoenix.png","category":"Fragments","detailsId":"fragment-of-the-phoenix"},{"id":"rage","name":"Mortal Rage","image":"/gen/image/WzI4LDE0LHsiZiI6IjJESXRlbXMvTWFwcy9VYmVyVmFhbDAxIiwic2NhbGUiOjF9XQ/9dca208434/UberVaal01.png","category":"Fragments","detailsId":"mortal-rage"},{"id":"reality-fragment","name":"Reality Fragment","image":"/gen/image/WzI4LDE0LHsiZiI6IjJESXRlbXMvTWFwcy9VYmVyQm9zc0tleU1hdmVuIiwic2NhbGUiOjF9XQ/20e155ad7d/UberBossKeyMaven.png","category":"Fragments","detailsId":"reality-fragment"},{"id":"reverent-fragment","name":"Reverent Fragment","image":"/gen/image/WzI4LDE0LHsiZiI6IjJESXRlbXMvTWFwcy9VYmVyQm9zc0tleUluY2FybmF0aW9uT2ZEcmVhZCIsInNjYWxlIjoxfV0/76b7ac3faa/UberBossKeyIncarnationOfDread.png","category":"Fragments","detailsId":"reverent-fragment"},{"id":"simulacrum-splinter","name":"Simulacrum Splinter","image":"/gen/image/WzI4LDE0LHsiZiI6IjJESXRlbXMvTWFwcy9EZWxpcml1bVNwbGludGVyIiwic2NhbGUiOjF9XQ/b36d2fcff6/DeliriumSplinter.png","category":"Fragments","detailsId":"simulacrum-splinter"},{"id":"synthesising-fragment","name":"Synthesising Fragment","image":"/gen/image/WzI4LDE0LHsiZiI6IjJESXRlbXMvTWFwcy9VYmVyQm9zc0tleUNvcnRleCIsInNjYWxlIjoxfV0/f97fadd4b1/UberBossKeyCortex.png","category":"Fragments","detailsId":"synthesising-fragment"},{"id":"the-black-barya","name":"The Black Barya","image":"/gen/image/WzI1LDE0LHsiZiI6IjJESXRlbXMvQ3VycmVuY3kvRmFyaWR1bi9GYXJpZHVuQm9zc0tleSIsInNjYWxlIjoxfV0/957d1ee2bd/FaridunBossKey.png","category":"Fragments","detailsId":"the-black-barya"},{"id":"timeless-eternal-emblem","name":"Timeless Eternal Emblem","image":"/gen/image/WzI4LDE0LHsiZiI6IjJESXRlbXMvTWFwcy9FdGVybmFsRW1waXJlRnJhZ21lbnQiLCJzY2FsZSI6MX1d/974fcca603/EternalEmpireFragment.png","category":"Fragments","detailsId":"timeless-eternal-emblem"},{"id":"timeless-karui-emblem","name":"Timeless Karui Emblem","image":"/gen/image/WzI4LDE0LHsiZiI6IjJESXRlbXMvTWFwcy9LYXJ1aUZyYWdtZW50Iiwic2NhbGUiOjF9XQ/c616b0ee65/KaruiFragment.png","category":"Fragments","detailsId":"timeless-karui-emblem"},{"id":"timeless-vaal-emblem","name":"Timeless Vaal Emblem","image":"/gen/image/WzI4LDE0LHsiZiI6IjJESXRlbXMvTWFwcy9WYWFsRnJhZ21lbnQiLCJzY2FsZSI6MX1d/1f8bc8f5ad/VaalFragment.png","category":"Fragments","detailsId":"timeless-vaal-emblem"},{"id":"uber-timeless-eternal-emblem","name":"Unrelenting Timeless Eternal Emblem","image":"/gen/image/WzI4LDE0LHsiZiI6IjJESXRlbXMvTWFwcy9UaW1lbGVzc0NvbmZsaWN0S2FydWkiLCJzY2FsZSI6MX1d/48dd647843/TimelessConflictKarui.png","category":"Fragments","detailsId":"unrelenting-timeless-eternal-emblem"},{"id":"uber-timeless-karui-emblem","name":"Unrelenting Timeless Karui Emblem","image":"/gen/image/WzI4LDE0LHsiZiI6IjJESXRlbXMvTWFwcy9UaW1lbGVzc0NvbmZsaWN0RXRlcm5hbCIsInNjYWxlIjoxfV0/f96320f889/TimelessConflictEternal.png","category":"Fragments","detailsId":"unrelenting-timeless-karui-emblem"},{"id":"uber-timeless-maraketh-emblem","name":"Unrelenting Timeless Maraketh Emblem","image":"/gen/image/WzI4LDE0LHsiZiI6IjJESXRlbXMvTWFwcy9UaW1lbGVzc0NvbmZsaWN0TWFyYWtldGgiLCJzY2FsZSI6MX1d/8eca6f27b3/TimelessConflictMaraketh.png","category":"Fragments","detailsId":"unrelenting-timeless-maraketh-emblem"},{"id":"uber-timeless-vaal-emblem","name":"Unrelenting Timeless Vaal Emblem","image":"/gen/image/WzI4LDE0LHsiZiI6IjJESXRlbXMvTWFwcy9UaW1lbGVzc0NvbmZsaWN0VmFhbCIsInNjYWxlIjoxfV0/895e0137f2/TimelessConflictVaal.png","category":"Fragments","detailsId":"unrelenting-timeless-vaal-emblem"},{"id":"veritanias-crest","name":"Veritania's Crest","image":"/gen/image/WzI4LDE0LHsiZiI6IjJESXRlbXMvTWFwcy9SZWRlZW1lckZyYWdtZW50Iiwic2NhbGUiOjF9XQ/86d22a34cc/RedeemerFragment.png","category":"Fragments","detailsId":"veritanias-crest"},{"id":"voidborn-reliquary-key","name":"Voidborn Reliquary Key","image":"/gen/image/WzI4LDE0LHsiZiI6IjJESXRlbXMvTWFwcy9Db3NtaWNDb3JlU3VwcG9ydGVyVmF1bHRLZXkiLCJzY2FsZSI6MX1d/1f2d34a36d/CosmicCoreSupporterVaultKey.png","category":"Fragments","detailsId":"voidborn-reliquary-key"}]}